{
    "id": "rct2.tt.hrbwal08",
    "authors": ["Frontier Studios"],
    "version": "1.0",
    "originalId": "0E24FA22|HRBWAL08|0B131ACD",
    "sourceGame": "rct2tt",
    "objectType": "scenery_large",
    "properties": {
        "price": 24,
        "removalPrice": -18,
        "cursor": "CURSOR_STATUE_DOWN",
        "isPhotogenic": true,
        "tiles": [
            {
                "x": 0,
                "y": 0,
                "clearance": 96,
                "walls": 9
            },
            {
                "x": 0,
                "y": 32,
                "clearance": 96,
                "walls": 3
            },
            {
                "x": 32,
                "y": 0,
                "clearance": 96,
                "walls": 8
            },
            {
                "x": 32,
                "y": 32,
                "clearance": 96,
                "walls": 2
            }
        ]
    },
    "images": ["$RCT2:OBJDATA/HRBWAL08.DAT[0..19]"],
    "strings": {
        "name": {
            "en-GB": "Harbour Wall Corner Piece",
            "fr-FR": "Section de virage du mur du port",
            "de-DE": "Hafenmauer Eckstück",
            "es-ES": "Sección de esquina de muro del puerto",
            "it-IT": "Tratto di curva del muro del porto",
            "nl-NL": "Havenmuur bochtstuk",
            "sv-SE": "Vägghörndel, hamn",
            "ko-KR": "항구 벽 구석 조각",
            "zh-TW": "港口牆牆角塊",
            "pt-BR": "Peça de Canto de Parede de Porto",
            "cs-CZ": "Přístav - roh",
            "pl-PL": "Narożnik muru przystani",
            "ru-RU": "Деталь гавани"
        }
    }
}
