{
    "id": "rct2.tjp2",
    "authors": ["Chris Sawyer", "Simon Foster"],
    "version": "1.0",
    "originalId": "0A188E81|TJP2    |F1DC517D",
    "sourceGame": ["rct2", "rct1aa"],
    "objectType": "scenery_small",
    "properties": {
        "price": 18,
        "removalPrice": 10,
        "cursor": "CURSOR_TREE_DOWN",
        "height": 36,
        "shape": "1/4",
        "isStackable": true
    },
    "images": ["$RCT2:OBJDATA/TJP2.DAT[0..3]"],
    "strings": {
        "name": {
            "en-GB": "Plant",
            "fr-FR": "Plante",
            "de-DE": "Pflanze",
            "es-ES": "Planta",
            "it-IT": "Pianta",
            "sv-SE": "Planta",
            "ko-KR": "잡초",
            "zh-CN": "植物",
            "zh-TW": "植物",
            "pt-BR": "Planta",
            "cs-CZ": "Rostlina",
            "ja-JP": "植物",
            "pl-PL": "Roślina",
            "ru-RU": "Куст"
        }
    }
}
