{
    "id": "rct1aa.ride.lay_down_trains",
    "authors": [
        "Chris Sawyer",
        "Simon Foster"
    ],
    "version": "1.0",
    "originalId": "00000000|#RCT1VEK|00000000",
    "sourceGame": "rct1aa",
    "isCompatibilityObject": true,
    "objectType": "ride",
    "properties": {
        "type": "lay_down_rc",
        "category": "rollercoaster",
        "limitAirTimeBonus": true,
        "maxCarsPerTrain": 6,
        "carColours": [
            [
                [
                    "bright_red",
                    "yellow",
                    "black"
                ]
            ],
            [
                [
                    "bright_green",
                    "yellow",
                    "black"
                ]
            ]
        ],
        "cars": [
            {
                "rotationFrameMask": 15,
                "spacing": 191488,
                "mass": 850,
                "numSeats": 4,
                "numSeatRows": 2,
                "frictionSoundId": 2,
                "soundRange": 2,
                "drawOrder": 6,
                "spriteGroups": {
                    "slopeFlat": 16,
                    "slopes12": 4,
                    "slopes25": 16,
                    "slopes42": 8,
                    "slopes60": 16,
                    "slopes75": 4,
                    "slopes90": 4,
                    "slopesLoop": 4,
                    "slopeInverted": 4,
                    "slopes8": 4,
                    "slopes16": 4,
                    "slopes50": 4,
                    "flatBanked22": 8,
                    "flatBanked45": 16,
                    "flatBanked67": 4,
                    "flatBanked90": 4,
                    "inlineTwists": 4,
                    "slopes12Banked22": 4,
                    "slopes8Banked22": 4,
                    "corkscrews": 4,
                    "restraintAnimation": 4
                },
                "hasInvertedSpriteSet": true,
                "spriteBoundsIncludeInvertedSet": true,
                "hasAdditionalColour1": true,
                "hasScreamingRiders": true,
                "loadingPositions": [
                    2,
                    -2,
                    2,
                    -2
                ]
            },
            {
                "rotationFrameMask": 15,
                "spacing": 191488,
                "mass": 850,
                "numSeats": 4,
                "numSeatRows": 2,
                "frictionSoundId": 2,
                "soundRange": 2,
                "drawOrder": 2,
                "spriteGroups": {
                    "slopeFlat": 16,
                    "slopes12": 4,
                    "slopes25": 16,
                    "slopes42": 8,
                    "slopes60": 16,
                    "slopeInverted": 4,
                    "slopes8": 4,
                    "slopes16": 4,
                    "slopes50": 4,
                    "flatBanked22": 8,
                    "flatBanked45": 16,
                    "slopes12Banked22": 4,
                    "slopes8Banked22": 4
                },
                "hasInvertedSpriteSet": true,
                "hasAdditionalColour1": true,
                "hasScreamingRiders": true,
                "loadingPositions": [
                    2,
                    -2,
                    2,
                    -2
                ]
            }
        ],
        "buildMenuPriority": 1
    },
    "images": [
        { "path": "images/preview.png", "format": "raw" },
        "",
        "",
        "$CSG[7106..7121]",
        "$CSG[7122]",
        "$CSG[7130]",
        "$CSG[7138]",
        "$CSG[7146]",
        "$CSG[7126]",
        "$CSG[7134]",
        "$CSG[7142]",
        "$CSG[7150]",
        "$CSG[7123]",
        "$CSG[7210..7212]",
        "$CSG[7131]",
        "$CSG[7213..7215]",
        "$CSG[7139]",
        "$CSG[7216..7218]",
        "$CSG[7147]",
        "$CSG[7219..7221]",
        "$CSG[7127]",
        "$CSG[7222..7224]",
        "$CSG[7135]",
        "$CSG[7225..7227]",
        "$CSG[7143]",
        "$CSG[7228..7230]",
        "$CSG[7151]",
        "$CSG[7231..7233]",
        "$CSG[7124]",
        "$CSG[7458]",
        "$CSG[7132]",
        "$CSG[7459]",
        "$CSG[7140]",
        "$CSG[7460]",
        "$CSG[7148]",
        "$CSG[7461]",
        "$CSG[7128]",
        "$CSG[7474]",
        "$CSG[7136]",
        "$CSG[7475]",
        "$CSG[7144]",
        "$CSG[7476]",
        "$CSG[7152]",
        "$CSG[7477]",
        "$CSG[7125]",
        "$CSG[7374..7376]",
        "$CSG[7133]",
        "$CSG[7377..7379]",
        "$CSG[7141]",
        "$CSG[7380..7382]",
        "$CSG[7149]",
        "$CSG[7383..7385]",
        "$CSG[7129]",
        "$CSG[7386..7388]",
        "$CSG[7137]",
        "$CSG[7389..7391]",
        "$CSG[7145]",
        "$CSG[7392..7394]",
        "$CSG[7153]",
        "$CSG[7395..7397]",
        "$CSG[7234..7237]",
        "$CSG[7266..7269]",
        "$CSG[7238..7241]",
        "$CSG[7270..7273]",
        "$CSG[7242..7245]",
        "$CSG[7274..7277]",
        "$CSG[7246..7249]",
        "$CSG[7278..7281]",
        "$CSG[7250..7253]",
        "$CSG[7282..7285]",
        "$CSG[7254..7257]",
        "$CSG[7286..7289]",
        "$CSG[7258..7261]",
        "$CSG[7290..7293]",
        "$CSG[7262..7265]",
        "$CSG[7450..7453]",
        "$CSG[7466..7469]",
        "$CSG[7454..7457]",
        "$CSG[7470..7473]",
        "$CSG[7462..7465]",
        "$CSG[7478..7481]",
        "$CSG[7186]",
        "$CSG[7498]",
        "$CSG[7187]",
        "$CSG[7499]",
        "$CSG[7188]",
        "$CSG[7500]",
        "$CSG[7189]",
        "$CSG[7501]",
        "$CSG[7190]",
        "$CSG[7502]",
        "$CSG[7191]",
        "$CSG[7503]",
        "$CSG[7192]",
        "$CSG[7504]",
        "$CSG[7193]",
        "$CSG[7505]",
        "$CSG[7154..7185]",
        "$CSG[7398]",
        "$CSG[7403]",
        "$CSG[7408]",
        "$CSG[7413]",
        "$CSG[7418]",
        "$CSG[7423]",
        "$CSG[7428]",
        "$CSG[7433]",
        "$CSG[7399]",
        "$CSG[7404]",
        "$CSG[7409]",
        "$CSG[7414]",
        "$CSG[7419]",
        "$CSG[7424]",
        "$CSG[7429]",
        "$CSG[7434]",
        "$CSG[7400]",
        "$CSG[7405]",
        "$CSG[7410]",
        "$CSG[7415]",
        "$CSG[7420]",
        "$CSG[7425]",
        "$CSG[7430]",
        "$CSG[7435]",
        "$CSG[7401]",
        "$CSG[7406]",
        "$CSG[7411]",
        "$CSG[7416]",
        "$CSG[7421]",
        "$CSG[7426]",
        "$CSG[7431]",
        "$CSG[7436]",
        "$CSG[7402]",
        "$CSG[7407]",
        "$CSG[7412]",
        "$CSG[7417]",
        "$CSG[7422]",
        "$CSG[7427]",
        "$CSG[7432]",
        "$CSG[7437]",
        "$CSG[7194..7209]",
        "$CSG[7482..7497]",
        "$CSG[7294..7373]",
        "$CSG[7438]",
        "$CSG[7441]",
        "$CSG[7444]",
        "$CSG[7447]",
        "$CSG[7439]",
        "$CSG[7442]",
        "$CSG[7445]",
        "$CSG[7448]",
        "$CSG[7440]",
        "$CSG[7443]",
        "$CSG[7446]",
        "$CSG[7449]",
        "$CSG[7942..7957]",
        "$CSG[7958]",
        "$CSG[7966]",
        "$CSG[7974]",
        "$CSG[7982]",
        "$CSG[7962]",
        "$CSG[7970]",
        "$CSG[7978]",
        "$CSG[7986]",
        "$CSG[7959]",
        "$CSG[8046..8048]",
        "$CSG[7967]",
        "$CSG[8049..8051]",
        "$CSG[7975]",
        "$CSG[8052..8054]",
        "$CSG[7983]",
        "$CSG[8055..8057]",
        "$CSG[7963]",
        "$CSG[8058..8060]",
        "$CSG[7971]",
        "$CSG[8061..8063]",
        "$CSG[7979]",
        "$CSG[8064..8066]",
        "$CSG[7987]",
        "$CSG[8067..8069]",
        "$CSG[7960]",
        "$CSG[8294]",
        "$CSG[7968]",
        "$CSG[8295]",
        "$CSG[7976]",
        "$CSG[8296]",
        "$CSG[7984]",
        "$CSG[8297]",
        "$CSG[7964]",
        "$CSG[8310]",
        "$CSG[7972]",
        "$CSG[8311]",
        "$CSG[7980]",
        "$CSG[8312]",
        "$CSG[7988]",
        "$CSG[8313]",
        "$CSG[7961]",
        "$CSG[8210..8212]",
        "$CSG[7969]",
        "$CSG[8213..8215]",
        "$CSG[7977]",
        "$CSG[8216..8218]",
        "$CSG[7985]",
        "$CSG[8219..8221]",
        "$CSG[7965]",
        "$CSG[8222..8224]",
        "$CSG[7973]",
        "$CSG[8225..8227]",
        "$CSG[7981]",
        "$CSG[8228..8230]",
        "$CSG[7989]",
        "$CSG[8231..8233]",
        "$CSG[8070..8073]",
        "$CSG[8102..8105]",
        "$CSG[8074..8077]",
        "$CSG[8106..8109]",
        "$CSG[8078..8081]",
        "$CSG[8110..8113]",
        "$CSG[8082..8085]",
        "$CSG[8114..8117]",
        "$CSG[8086..8089]",
        "$CSG[8118..8121]",
        "$CSG[8090..8093]",
        "$CSG[8122..8125]",
        "$CSG[8094..8097]",
        "$CSG[8126..8129]",
        "$CSG[8098..8101]",
        "$CSG[8286..8289]",
        "$CSG[8302..8305]",
        "$CSG[8290..8293]",
        "$CSG[8306..8309]",
        "$CSG[8298..8301]",
        "$CSG[8314..8317]",
        "$CSG[8022]",
        "$CSG[8334]",
        "$CSG[8023]",
        "$CSG[8335]",
        "$CSG[8024]",
        "$CSG[8336]",
        "$CSG[8025]",
        "$CSG[8337]",
        "$CSG[8026]",
        "$CSG[8338]",
        "$CSG[8027]",
        "$CSG[8339]",
        "$CSG[8028]",
        "$CSG[8340]",
        "$CSG[8029]",
        "$CSG[8341]",
        "$CSG[7990..8021]",
        "$CSG[8234]",
        "$CSG[8239]",
        "$CSG[8244]",
        "$CSG[8249]",
        "$CSG[8254]",
        "$CSG[8259]",
        "$CSG[8264]",
        "$CSG[8269]",
        "$CSG[8235]",
        "$CSG[8240]",
        "$CSG[8245]",
        "$CSG[8250]",
        "$CSG[8255]",
        "$CSG[8260]",
        "$CSG[8265]",
        "$CSG[8270]",
        "$CSG[8236]",
        "$CSG[8241]",
        "$CSG[8246]",
        "$CSG[8251]",
        "$CSG[8256]",
        "$CSG[8261]",
        "$CSG[8266]",
        "$CSG[8271]",
        "$CSG[8237]",
        "$CSG[8242]",
        "$CSG[8247]",
        "$CSG[8252]",
        "$CSG[8257]",
        "$CSG[8262]",
        "$CSG[8267]",
        "$CSG[8272]",
        "$CSG[8238]",
        "$CSG[8243]",
        "$CSG[8248]",
        "$CSG[8253]",
        "$CSG[8258]",
        "$CSG[8263]",
        "$CSG[8268]",
        "$CSG[8273]",
        "$CSG[8030..8045]",
        "$CSG[8318..8333]",
        "$CSG[8130..8209]",
        "$CSG[8274]",
        "$CSG[8277]",
        "$CSG[8280]",
        "$CSG[8283]",
        "$CSG[8275]",
        "$CSG[8278]",
        "$CSG[8281]",
        "$CSG[8284]",
        "$CSG[8276]",
        "$CSG[8279]",
        "$CSG[8282]",
        "$CSG[8285]",
        "$CSG[8778..8793]",
        "$CSG[8794]",
        "$CSG[8802]",
        "$CSG[8810]",
        "$CSG[8818]",
        "$CSG[8798]",
        "$CSG[8806]",
        "$CSG[8814]",
        "$CSG[8822]",
        "$CSG[8795]",
        "$CSG[8882..8884]",
        "$CSG[8803]",
        "$CSG[8885..8887]",
        "$CSG[8811]",
        "$CSG[8888..8890]",
        "$CSG[8819]",
        "$CSG[8891..8893]",
        "$CSG[8799]",
        "$CSG[8894..8896]",
        "$CSG[8807]",
        "$CSG[8897..8899]",
        "$CSG[8815]",
        "$CSG[8900..8902]",
        "$CSG[8823]",
        "$CSG[8903..8905]",
        "$CSG[8796]",
        "$CSG[9130]",
        "$CSG[8804]",
        "$CSG[9131]",
        "$CSG[8812]",
        "$CSG[9132]",
        "$CSG[8820]",
        "$CSG[9133]",
        "$CSG[8800]",
        "$CSG[9146]",
        "$CSG[8808]",
        "$CSG[9147]",
        "$CSG[8816]",
        "$CSG[9148]",
        "$CSG[8824]",
        "$CSG[9149]",
        "$CSG[8797]",
        "$CSG[9046..9048]",
        "$CSG[8805]",
        "$CSG[9049..9051]",
        "$CSG[8813]",
        "$CSG[9052..9054]",
        "$CSG[8821]",
        "$CSG[9055..9057]",
        "$CSG[8801]",
        "$CSG[9058..9060]",
        "$CSG[8809]",
        "$CSG[9061..9063]",
        "$CSG[8817]",
        "$CSG[9064..9066]",
        "$CSG[8825]",
        "$CSG[9067..9069]",
        "$CSG[8906..8909]",
        "$CSG[8938..8941]",
        "$CSG[8910..8913]",
        "$CSG[8942..8945]",
        "$CSG[8914..8917]",
        "$CSG[8946..8949]",
        "$CSG[8918..8921]",
        "$CSG[8950..8953]",
        "$CSG[8922..8925]",
        "$CSG[8954..8957]",
        "$CSG[8926..8929]",
        "$CSG[8958..8961]",
        "$CSG[8930..8933]",
        "$CSG[8962..8965]",
        "$CSG[8934..8937]",
        "$CSG[9122..9125]",
        "$CSG[9138..9141]",
        "$CSG[9126..9129]",
        "$CSG[9142..9145]",
        "$CSG[9134..9137]",
        "$CSG[9150..9153]",
        "$CSG[8858]",
        "$CSG[9170]",
        "$CSG[8859]",
        "$CSG[9171]",
        "$CSG[8860]",
        "$CSG[9172]",
        "$CSG[8861]",
        "$CSG[9173]",
        "$CSG[8862]",
        "$CSG[9174]",
        "$CSG[8863]",
        "$CSG[9175]",
        "$CSG[8864]",
        "$CSG[9176]",
        "$CSG[8865]",
        "$CSG[9177]",
        "$CSG[8826..8857]",
        "$CSG[9070]",
        "$CSG[9075]",
        "$CSG[9080]",
        "$CSG[9085]",
        "$CSG[9090]",
        "$CSG[9095]",
        "$CSG[9100]",
        "$CSG[9105]",
        "$CSG[9071]",
        "$CSG[9076]",
        "$CSG[9081]",
        "$CSG[9086]",
        "$CSG[9091]",
        "$CSG[9096]",
        "$CSG[9101]",
        "$CSG[9106]",
        "$CSG[9072]",
        "$CSG[9077]",
        "$CSG[9082]",
        "$CSG[9087]",
        "$CSG[9092]",
        "$CSG[9097]",
        "$CSG[9102]",
        "$CSG[9107]",
        "$CSG[9073]",
        "$CSG[9078]",
        "$CSG[9083]",
        "$CSG[9088]",
        "$CSG[9093]",
        "$CSG[9098]",
        "$CSG[9103]",
        "$CSG[9108]",
        "$CSG[9074]",
        "$CSG[9079]",
        "$CSG[9084]",
        "$CSG[9089]",
        "$CSG[9094]",
        "$CSG[9099]",
        "$CSG[9104]",
        "$CSG[9109]",
        "$CSG[8866..8881]",
        "$CSG[9154..9169]",
        "$CSG[8966..9045]",
        "$CSG[9110]",
        "$CSG[9113]",
        "$CSG[9116]",
        "$CSG[9119]",
        "$CSG[9111]",
        "$CSG[9114]",
        "$CSG[9117]",
        "$CSG[9120]",
        "$CSG[9112]",
        "$CSG[9115]",
        "$CSG[9118]",
        "$CSG[9121]",
        "$CSG[7264]",
        { "gx": "$CSG[7507]", "y": -5 },
        { "gx": "$CSG[7508]", "y": -5 },
        { "gx": "$CSG[7509]", "y": -5 },
        "$CSG[7265]",
        { "gx": "$CSG[7511]", "y": -4 },
        { "gx": "$CSG[7512]", "y": -3 },
        { "gx": "$CSG[7513]", "y": -4 },
        "$CSG[7262]",
        { "gx": "$CSG[7515]", "y": -5 },
        { "gx": "$CSG[7516]", "y": -5 },
        { "gx": "$CSG[7517]", "y": -5 },
        "$CSG[7263]",
        { "gx": "$CSG[7519]", "y": -4 },
        { "gx": "$CSG[7520]", "y": -2 },
        { "gx": "$CSG[7521]", "y": -4 },
        { "gx": "$CSG[7522]", "y": -5 },
        { "gx": "$CSG[7530]", "y": -4 },
        { "gx": "$CSG[7538]", "y": -4 },
        { "gx": "$CSG[7546]", "y": -6 },
        { "gx": "$CSG[7526]", "y": -4 },
        { "gx": "$CSG[7534]", "y": -7 },
        { "gx": "$CSG[7542]", "y": -7 },
        { "gx": "$CSG[7550]", "y": -4 },
        { "gx": "$CSG[7523]", "y": -6 },
        { "gx": "$CSG[7610]", "y": -7 },
        { "gx": "$CSG[7611]", "y": -6 },
        { "gx": "$CSG[7612]", "y": -5 },
        { "gx": "$CSG[7531]", "y": -4 },
        { "gx": "$CSG[7613]", "y": -2 },
        { "gx": "$CSG[7614]", "y": 0 },
        { "gx": "$CSG[7615]", "y": -2 },
        { "gx": "$CSG[7539]", "y": -3 },
        { "gx": "$CSG[7616]", "y": -5 },
        { "gx": "$CSG[7617]", "y": -6 },
        { "gx": "$CSG[7618]", "y": -7 },
        { "gx": "$CSG[7547]", "y": -6 },
        { "gx": "$CSG[7619]", "y": -6 },
        { "gx": "$CSG[7620]", "y": -7 },
        { "gx": "$CSG[7621]", "y": -6 },
        { "gx": "$CSG[7527]", "y": -3 },
        { "gx": "$CSG[7622]", "y": -5 },
        { "gx": "$CSG[7623]", "y": -6 },
        { "gx": "$CSG[7624]", "y": -8 },
        { "gx": "$CSG[7535]", "y": -9 },
        { "gx": "$CSG[7625]", "y": -9 },
        { "gx": "$CSG[7626]", "y": -8 },
        { "gx": "$CSG[7627]", "y": -9 },
        { "gx": "$CSG[7543]", "y": -9 },
        { "gx": "$CSG[7628]", "y": -8 },
        { "gx": "$CSG[7629]", "y": -6 },
        { "gx": "$CSG[7630]", "y": -5 },
        { "gx": "$CSG[7551]", "y": -4 },
        { "gx": "$CSG[7631]", "y": -2 },
        { "gx": "$CSG[7632]", "y": 0 },
        { "gx": "$CSG[7633]", "y": -2 },
        { "gx": "$CSG[7524]", "y": -8 },
        { "gx": "$CSG[7894]", "y": -7 },
        { "gx": "$CSG[7532]", "y": -5 },
        { "gx": "$CSG[7895]", "y": 0 },
        { "gx": "$CSG[7540]", "y": -5 },
        { "gx": "$CSG[7896]", "y": -7 },
        { "gx": "$CSG[7548]", "y": -8 },
        { "gx": "$CSG[7897]", "y": -10 },
        { "gx": "$CSG[7528]", "y": -4 },
        { "gx": "$CSG[7910]", "y": -10 },
        { "gx": "$CSG[7536]", "y": -12 },
        { "gx": "$CSG[7911]", "y": -11 },
        { "gx": "$CSG[7544]", "y": -13 },
        { "gx": "$CSG[7912]", "y": -10 },
        { "gx": "$CSG[7552]", "y": -5 },
        { "gx": "$CSG[7913]", "y": 0 },
        { "gx": "$CSG[7525]", "y": -10 },
        { "gx": "$CSG[7774]", "y": -9 },
        { "gx": "$CSG[7775]", "y": -8 },
        { "gx": "$CSG[7776]", "y": -7 },
        { "gx": "$CSG[7533]", "y": -6 },
        { "gx": "$CSG[7777]", "y": -3 },
        { "gx": "$CSG[7778]", "y": -2 },
        { "gx": "$CSG[7779]", "y": -3 },
        { "gx": "$CSG[7541]", "y": -6 },
        { "gx": "$CSG[7780]", "y": -7 },
        { "gx": "$CSG[7781]", "y": -8 },
        { "gx": "$CSG[7782]", "y": -9 },
        { "gx": "$CSG[7549]", "y": -10 },
        { "gx": "$CSG[7783]", "y": -12 },
        { "gx": "$CSG[7784]", "y": -12 },
        { "gx": "$CSG[7785]", "y": -12 },
        { "gx": "$CSG[7529]", "y": -8 },
        { "gx": "$CSG[7786]", "y": -10 },
        { "gx": "$CSG[7787]", "y": -13 },
        { "gx": "$CSG[7788]", "y": -15 },
        { "gx": "$CSG[7537]", "y": -15 },
        { "gx": "$CSG[7789]", "y": -15 },
        { "gx": "$CSG[7790]", "y": -13 },
        { "gx": "$CSG[7791]", "y": -15 },
        { "gx": "$CSG[7545]", "y": -15 },
        { "gx": "$CSG[7792]", "y": -15 },
        { "gx": "$CSG[7793]", "y": -13 },
        { "gx": "$CSG[7794]", "y": -10 },
        { "gx": "$CSG[7553]", "y": -7 },
        { "gx": "$CSG[7795]", "y": -4 },
        { "gx": "$CSG[7796]", "y": -3 },
        { "gx": "$CSG[7797]", "y": -4 },
        "$CSG[7114]",
        "$CSG[7118]",
        "$CSG[7106]",
        "$CSG[7110]",
        { "gx": "$CSG[7886]", "y": -5 },
        { "gx": "$CSG[7887]", "y": -1 },
        { "gx": "$CSG[7888]", "y": -5 },
        { "gx": "$CSG[7889]", "y": -4 },
        { "gx": "$CSG[7902]", "y": -5 },
        { "gx": "$CSG[7903]", "y": -5 },
        { "gx": "$CSG[7904]", "y": -5 },
        { "gx": "$CSG[7905]", "y": -1 },
        { "gx": "$CSG[7890]", "y": -6 },
        { "gx": "$CSG[7891]", "y": 0 },
        { "gx": "$CSG[7892]", "y": -6 },
        { "gx": "$CSG[7893]", "y": -6 },
        { "gx": "$CSG[7906]", "y": -6 },
        { "gx": "$CSG[7907]", "y": -7 },
        { "gx": "$CSG[7908]", "y": -6 },
        { "gx": "$CSG[7909]", "y": -1 },
        { "gx": "$CSG[7898]", "y": -8 },
        { "gx": "$CSG[7899]", "y": -1 },
        { "gx": "$CSG[7900]", "y": -8 },
        { "gx": "$CSG[7901]", "y": -11 },
        { "gx": "$CSG[7914]", "y": -11 },
        { "gx": "$CSG[7915]", "y": -12 },
        { "gx": "$CSG[7916]", "y": -11 },
        { "gx": "$CSG[7917]", "y": -1 },
        { "gx": "$CSG[7586]", "y": -1 },
        { "gx": "$CSG[7934]", "y": -1 },
        { "gx": "$CSG[7587]", "y": -1 },
        { "gx": "$CSG[7935]", "y": -6 },
        { "gx": "$CSG[7588]", "y": -9 },
        { "gx": "$CSG[7936]", "y": -8 },
        { "gx": "$CSG[7589]", "y": -8 },
        { "gx": "$CSG[7937]", "y": -5 },
        { "gx": "$CSG[7590]", "y": -8 },
        { "gx": "$CSG[7938]", "y": -8 },
        { "gx": "$CSG[7591]", "y": -8 },
        { "gx": "$CSG[7939]", "y": -6 },
        { "gx": "$CSG[7592]", "y": -1 },
        { "gx": "$CSG[7940]", "y": -1 },
        { "gx": "$CSG[7593]", "y": -1 },
        { "gx": "$CSG[7941]", "y": -5 },
        { "gx": "$CSG[7554]", "y": -5 },
        { "gx": "$CSG[7555]", "y": -4 },
        { "gx": "$CSG[7556]", "y": -3 },
        { "gx": "$CSG[7557]", "y": -3 },
        { "gx": "$CSG[7558]", "y": -5 },
        { "gx": "$CSG[7559]", "y": -8 },
        { "gx": "$CSG[7560]", "y": -10 },
        { "gx": "$CSG[7561]", "y": -12 },
        { "gx": "$CSG[7562]", "y": -13 },
        { "gx": "$CSG[7563]", "y": -13 },
        { "gx": "$CSG[7564]", "y": -12 },
        { "gx": "$CSG[7565]", "y": -11 },
        { "gx": "$CSG[7566]", "y": -10 },
        { "gx": "$CSG[7567]", "y": -9 },
        { "gx": "$CSG[7568]", "y": -8 },
        { "gx": "$CSG[7569]", "y": -7 },
        { "gx": "$CSG[7570]", "y": -10 },
        { "gx": "$CSG[7571]", "y": -11 },
        { "gx": "$CSG[7572]", "y": -12 },
        { "gx": "$CSG[7573]", "y": -13 },
        { "gx": "$CSG[7574]", "y": -13 },
        { "gx": "$CSG[7575]", "y": -12 },
        { "gx": "$CSG[7576]", "y": -10 },
        { "gx": "$CSG[7577]", "y": -7 },
        { "gx": "$CSG[7578]", "y": -5 },
        { "gx": "$CSG[7579]", "y": -3 },
        { "gx": "$CSG[7580]", "y": -3 },
        { "gx": "$CSG[7581]", "y": -4 },
        { "gx": "$CSG[7582]", "y": -5 },
        { "gx": "$CSG[7583]", "y": -7 },
        { "gx": "$CSG[7584]", "y": -8 },
        { "gx": "$CSG[7585]", "y": -9 },
        { "gx": "$CSG[7594]", "y": -2 },
        { "gx": "$CSG[7595]", "y": -1 },
        { "gx": "$CSG[7596]", "y": -8 },
        { "gx": "$CSG[7597]", "y": -8 },
        { "gx": "$CSG[7598]", "y": -8 },
        { "gx": "$CSG[7599]", "y": -7 },
        { "gx": "$CSG[7600]", "y": -1 },
        { "gx": "$CSG[7601]", "y": -2 },
        { "gx": "$CSG[7602]", "y": -1 },
        { "gx": "$CSG[7603]", "y": -3 },
        { "gx": "$CSG[7604]", "y": -11 },
        { "gx": "$CSG[7605]", "y": -7 },
        { "gx": "$CSG[7606]", "y": -8 },
        { "gx": "$CSG[7607]", "y": -11 },
        { "gx": "$CSG[7608]", "y": -3 },
        { "gx": "$CSG[7609]", "y": -1 },
        { "gx": "$CSG[7918]", "y": -2 },
        { "gx": "$CSG[7919]", "y": -5 },
        { "gx": "$CSG[7920]", "y": -9 },
        { "gx": "$CSG[7921]", "y": -5 },
        { "gx": "$CSG[7922]", "y": -9 },
        { "gx": "$CSG[7923]", "y": -5 },
        { "gx": "$CSG[7924]", "y": -2 },
        { "gx": "$CSG[7925]", "y": -5 },
        { "gx": "$CSG[7926]", "y": -2 },
        { "gx": "$CSG[7927]", "y": -8 },
        { "gx": "$CSG[7928]", "y": -8 },
        { "gx": "$CSG[7929]", "y": -4 },
        { "gx": "$CSG[7930]", "y": -8 },
        { "gx": "$CSG[7931]", "y": -8 },
        { "gx": "$CSG[7932]", "y": -2 },
        { "gx": "$CSG[7933]", "y": -4 },
        "$CSG[8100]",
        { "gx": "$CSG[8343]", "y": 6 },
        { "gx": "$CSG[8344]", "y": 18 },
        { "gx": "$CSG[8345]", "y": 26 },
        "$CSG[8101]",
        { "gx": "$CSG[8347]", "y": 5 },
        { "gx": "$CSG[8348]", "y": 5 },
        { "gx": "$CSG[8349]", "y": 7 },
        "$CSG[8098]",
        { "gx": "$CSG[8351]", "y": 11 },
        { "gx": "$CSG[8352]", "y": 10 },
        { "gx": "$CSG[8353]", "y": 10 },
        "$CSG[8099]",
        { "gx": "$CSG[8355]", "y": 7 },
        { "gx": "$CSG[8356]", "y": 10 },
        { "gx": "$CSG[8357]", "y": 12 },
        { "gx": "$CSG[8358]", "y": 10 },
        { "gx": "$CSG[8366]", "y": 3 },
        { "gx": "$CSG[8374]", "y": 9 },
        { "gx": "$CSG[8382]", "y": 8 },
        { "gx": "$CSG[8362]", "y": 8 },
        { "gx": "$CSG[8370]", "y": 3 },
        { "gx": "$CSG[8378]", "y": 8 },
        { "gx": "$CSG[8386]", "y": 10 },
        { "gx": "$CSG[8359]", "y": 10 },
        { "gx": "$CSG[8446]", "y": 18 },
        { "gx": "$CSG[8447]", "y": 26 },
        { "gx": "$CSG[8448]", "y": 4 },
        { "gx": "$CSG[8367]", "y": 2 },
        { "gx": "$CSG[8449]", "y": 5 },
        { "gx": "$CSG[8450]", "y": 7 },
        { "gx": "$CSG[8451]", "y": 8 },
        { "gx": "$CSG[8375]", "y": 8 },
        { "gx": "$CSG[8452]", "y": 8 },
        { "gx": "$CSG[8453]", "y": 7 },
        { "gx": "$CSG[8454]", "y": 7 },
        { "gx": "$CSG[8383]", "y": 6 },
        { "gx": "$CSG[8455]", "y": 4 },
        { "gx": "$CSG[8456]", "y": 2 },
        { "gx": "$CSG[8457]", "y": 12 },
        { "gx": "$CSG[8363]", "y": 4 },
        { "gx": "$CSG[8458]", "y": 3 },
        { "gx": "$CSG[8459]", "y": -1 },
        { "gx": "$CSG[8460]", "y": 13 },
        { "gx": "$CSG[8371]", "y": 3 },
        { "gx": "$CSG[8461]", "y": 4 },
        { "gx": "$CSG[8462]", "y": 2 },
        { "gx": "$CSG[8463]", "y": 2 },
        { "gx": "$CSG[8379]", "y": 5 },
        { "gx": "$CSG[8464]", "y": 4 },
        { "gx": "$CSG[8465]", "y": 7 },
        { "gx": "$CSG[8466]", "y": 10 },
        { "gx": "$CSG[8387]", "y": 10 },
        { "gx": "$CSG[8467]", "y": 10 },
        { "gx": "$CSG[8468]", "y": 9 },
        { "gx": "$CSG[8469]", "y": 9 },
        { "gx": "$CSG[8360]", "y": 26 },
        { "gx": "$CSG[8730]", "y": 2 },
        { "gx": "$CSG[8368]", "y": 1 },
        { "gx": "$CSG[8731]", "y": 6 },
        { "gx": "$CSG[8376]", "y": 6 },
        { "gx": "$CSG[8732]", "y": 5 },
        { "gx": "$CSG[8384]", "y": 3 },
        { "gx": "$CSG[8733]", "y": -1 },
        { "gx": "$CSG[8364]", "y": 3 },
        { "gx": "$CSG[8746]", "y": -5 },
        { "gx": "$CSG[8372]", "y": 26 },
        { "gx": "$CSG[8747]", "y": -1 },
        { "gx": "$CSG[8380]", "y": -1 },
        { "gx": "$CSG[8748]", "y": 2 },
        { "gx": "$CSG[8388]", "y": 8 },
        { "gx": "$CSG[8749]", "y": 8 },
        { "gx": "$CSG[8361]", "y": 11 },
        { "gx": "$CSG[8610]", "y": 26 },
        { "gx": "$CSG[8611]", "y": -5 },
        { "gx": "$CSG[8612]", "y": -3 },
        { "gx": "$CSG[8369]", "y": -1 },
        { "gx": "$CSG[8613]", "y": 2 },
        { "gx": "$CSG[8614]", "y": 4 },
        { "gx": "$CSG[8615]", "y": 5 },
        { "gx": "$CSG[8377]", "y": 5 },
        { "gx": "$CSG[8616]", "y": 4 },
        { "gx": "$CSG[8617]", "y": 2 },
        { "gx": "$CSG[8618]", "y": 1 },
        { "gx": "$CSG[8385]", "y": 1 },
        { "gx": "$CSG[8619]", "y": -2 },
        { "gx": "$CSG[8620]", "y": -4 },
        { "gx": "$CSG[8621]", "y": -3 },
        { "gx": "$CSG[8365]", "y": -1 },
        { "gx": "$CSG[8622]", "y": -6 },
        { "gx": "$CSG[8623]", "y": -9 },
        { "gx": "$CSG[8624]", "y": -12 },
        { "gx": "$CSG[8373]", "y": 26 },
        { "gx": "$CSG[8625]", "y": -6 },
        { "gx": "$CSG[8626]", "y": -11 },
        { "gx": "$CSG[8627]", "y": -8 },
        { "gx": "$CSG[8381]", "y": -6 },
        { "gx": "$CSG[8628]", "y": -5 },
        { "gx": "$CSG[8629]", "y": -2 },
        { "gx": "$CSG[8630]", "y": -8 },
        { "gx": "$CSG[8389]", "y": 3 },
        { "gx": "$CSG[8631]", "y": 4 },
        { "gx": "$CSG[8632]", "y": 5 },
        { "gx": "$CSG[8633]", "y": 2 },
        "$CSG[7950]",
        "$CSG[7954]",
        "$CSG[7942]",
        "$CSG[7946]",
        { "gx": "$CSG[8722]", "y": 26 },
        { "gx": "$CSG[8723]", "y": 7 },
        { "gx": "$CSG[8724]", "y": 10 },
        { "gx": "$CSG[8725]", "y": 15 },
        { "gx": "$CSG[8738]", "y": 17 },
        { "gx": "$CSG[8739]", "y": 4 },
        { "gx": "$CSG[8740]", "y": 10 },
        { "gx": "$CSG[8741]", "y": 11 },
        { "gx": "$CSG[8726]", "y": 19 },
        { "gx": "$CSG[8727]", "y": 7 },
        { "gx": "$CSG[8728]", "y": 9 },
        { "gx": "$CSG[8729]", "y": 3 },
        { "gx": "$CSG[8742]", "y": 26 },
        { "gx": "$CSG[8743]", "y": 2 },
        { "gx": "$CSG[8744]", "y": 8 },
        { "gx": "$CSG[8745]", "y": 10 },
        { "gx": "$CSG[8734]", "y": 0 },
        { "gx": "$CSG[8735]", "y": 5 },
        { "gx": "$CSG[8736]", "y": 4 },
        { "gx": "$CSG[8737]", "y": -3 },
        { "gx": "$CSG[8750]", "y": -7 },
        { "gx": "$CSG[8751]", "y": -2 },
        { "gx": "$CSG[8752]", "y": 0 },
        { "gx": "$CSG[8753]", "y": 7 },
        { "gx": "$CSG[8422]", "y": 14 },
        { "gx": "$CSG[8770]", "y": 10 },
        { "gx": "$CSG[8423]", "y": 8 },
        { "gx": "$CSG[8771]", "y": 10 },
        { "gx": "$CSG[8424]", "y": 12 },
        { "gx": "$CSG[8772]", "y": 12 },
        { "gx": "$CSG[8425]", "y": 11 },
        { "gx": "$CSG[8773]", "y": 15 },
        { "gx": "$CSG[8426]", "y": 3 },
        { "gx": "$CSG[8774]", "y": 26 },
        { "gx": "$CSG[8427]", "y": -3 },
        { "gx": "$CSG[8775]", "y": 0 },
        { "gx": "$CSG[8428]", "y": 6 },
        { "gx": "$CSG[8776]", "y": 7 },
        { "gx": "$CSG[8429]", "y": 5 },
        { "gx": "$CSG[8777]", "y": 3 },
        { "gx": "$CSG[8390]", "y": 14 },
        { "gx": "$CSG[8391]", "y": 10 },
        { "gx": "$CSG[8392]", "y": 10 },
        { "gx": "$CSG[8393]", "y": 8 },
        { "gx": "$CSG[8394]", "y": 6 },
        { "gx": "$CSG[8395]", "y": 7 },
        { "gx": "$CSG[8396]", "y": 7 },
        { "gx": "$CSG[8397]", "y": 9 },
        { "gx": "$CSG[8398]", "y": 12 },
        { "gx": "$CSG[8399]", "y": 12 },
        { "gx": "$CSG[8400]", "y": 12 },
        { "gx": "$CSG[8401]", "y": 7 },
        { "gx": "$CSG[8402]", "y": 9 },
        { "gx": "$CSG[8403]", "y": 11 },
        { "gx": "$CSG[8404]", "y": 12 },
        { "gx": "$CSG[8405]", "y": 13 },
        { "gx": "$CSG[8406]", "y": -9 },
        { "gx": "$CSG[8407]", "y": -11 },
        { "gx": "$CSG[8408]", "y": -12 },
        { "gx": "$CSG[8409]", "y": -12 },
        { "gx": "$CSG[8410]", "y": -11 },
        { "gx": "$CSG[8411]", "y": -8 },
        { "gx": "$CSG[8412]", "y": -6 },
        { "gx": "$CSG[8413]", "y": -3 },
        { "gx": "$CSG[8414]", "y": 1 },
        { "gx": "$CSG[8415]", "y": 3 },
        { "gx": "$CSG[8416]", "y": 4 },
        { "gx": "$CSG[8417]", "y": 3 },
        { "gx": "$CSG[8418]", "y": 1 },
        { "gx": "$CSG[8419]", "y": -2 },
        { "gx": "$CSG[8420]", "y": -5 },
        { "gx": "$CSG[8421]", "y": -7 },
        { "gx": "$CSG[8430]", "y": 14 },
        { "gx": "$CSG[8431]", "y": 7 },
        { "gx": "$CSG[8432]", "y": 10 },
        { "gx": "$CSG[8433]", "y": 9 },
        { "gx": "$CSG[8434]", "y": 4 },
        { "gx": "$CSG[8435]", "y": -3 },
        { "gx": "$CSG[8436]", "y": 7 },
        { "gx": "$CSG[8437]", "y": 5 },
        { "gx": "$CSG[8438]", "y": 13 },
        { "gx": "$CSG[8439]", "y": 9 },
        { "gx": "$CSG[8440]", "y": 9 },
        { "gx": "$CSG[8441]", "y": 11 },
        { "gx": "$CSG[8442]", "y": 1 },
        { "gx": "$CSG[8443]", "y": -2 },
        { "gx": "$CSG[8444]", "y": 5 },
        { "gx": "$CSG[8445]", "y": 6 },
        { "gx": "$CSG[8754]", "y": 6 },
        { "gx": "$CSG[8755]", "y": 8 },
        { "gx": "$CSG[8756]", "y": 12 },
        { "gx": "$CSG[8757]", "y": 15 },
        { "gx": "$CSG[8758]", "y": 26 },
        { "gx": "$CSG[8759]", "y": 2 },
        { "gx": "$CSG[8760]", "y": 7 },
        { "gx": "$CSG[8761]", "y": 0 },
        { "gx": "$CSG[8762]", "y": 8 },
        { "gx": "$CSG[8763]", "y": 9 },
        { "gx": "$CSG[8764]", "y": 11 },
        { "gx": "$CSG[8765]", "y": 11 },
        { "gx": "$CSG[8766]", "y": 26 },
        { "gx": "$CSG[8767]", "y": -2 },
        { "gx": "$CSG[8768]", "y": 8 },
        { "gx": "$CSG[8769]", "y": 3 },
        "$CSG[8936]",
        { "gx": "$CSG[9179]", "y": 10 },
        { "gx": "$CSG[9180]", "y": 10 },
        { "gx": "$CSG[9181]", "y": 10 },
        "$CSG[8937]",
        { "gx": "$CSG[9183]", "y": 8 },
        { "gx": "$CSG[9184]", "y": 5 },
        { "gx": "$CSG[9185]", "y": 5 },
        "$CSG[8934]",
        { "gx": "$CSG[9187]", "y": 11 },
        { "gx": "$CSG[9188]", "y": 11 },
        { "gx": "$CSG[9189]", "y": 6 },
        "$CSG[8935]",
        { "gx": "$CSG[9191]", "y": 12 },
        { "gx": "$CSG[9192]", "y": 15 },
        { "gx": "$CSG[9193]", "y": 7 },
        { "gx": "$CSG[9194]", "y": 7 },
        { "gx": "$CSG[9202]", "y": 9 },
        { "gx": "$CSG[9210]", "y": 4 },
        { "gx": "$CSG[9218]", "y": 10 },
        { "gx": "$CSG[9198]", "y": 10 },
        { "gx": "$CSG[9206]", "y": 7 },
        { "gx": "$CSG[9214]", "y": 3 },
        { "gx": "$CSG[9222]", "y": 8 },
        { "gx": "$CSG[9195]", "y": 6 },
        { "gx": "$CSG[9282]", "y": 7 },
        { "gx": "$CSG[9283]", "y": 7 },
        { "gx": "$CSG[9284]", "y": 8 },
        { "gx": "$CSG[9203]", "y": 8 },
        { "gx": "$CSG[9285]", "y": 8 },
        { "gx": "$CSG[9286]", "y": 8 },
        { "gx": "$CSG[9287]", "y": 5 },
        { "gx": "$CSG[9211]", "y": 3 },
        { "gx": "$CSG[9288]", "y": 4 },
        { "gx": "$CSG[9289]", "y": 11 },
        { "gx": "$CSG[9290]", "y": 26 },
        { "gx": "$CSG[9219]", "y": 10 },
        { "gx": "$CSG[9291]", "y": 12 },
        { "gx": "$CSG[9292]", "y": 2 },
        { "gx": "$CSG[9293]", "y": 4 },
        { "gx": "$CSG[9199]", "y": 10 },
        { "gx": "$CSG[9294]", "y": 9 },
        { "gx": "$CSG[9295]", "y": 7 },
        { "gx": "$CSG[9296]", "y": 4 },
        { "gx": "$CSG[9207]", "y": 4 },
        { "gx": "$CSG[9297]", "y": 2 },
        { "gx": "$CSG[9298]", "y": 2 },
        { "gx": "$CSG[9299]", "y": 4 },
        { "gx": "$CSG[9215]", "y": 3 },
        { "gx": "$CSG[9300]", "y": 26 },
        { "gx": "$CSG[9301]", "y": -1 },
        { "gx": "$CSG[9302]", "y": 2 },
        { "gx": "$CSG[9223]", "y": 4 },
        { "gx": "$CSG[9303]", "y": 10 },
        { "gx": "$CSG[9304]", "y": 10 },
        { "gx": "$CSG[9305]", "y": 9 },
        { "gx": "$CSG[9196]", "y": 3 },
        { "gx": "$CSG[9566]", "y": 4 },
        { "gx": "$CSG[9204]", "y": 6 },
        { "gx": "$CSG[9567]", "y": 6 },
        { "gx": "$CSG[9212]", "y": 1 },
        { "gx": "$CSG[9568]", "y": 3 },
        { "gx": "$CSG[9220]", "y": 26 },
        { "gx": "$CSG[9569]", "y": -1 },
        { "gx": "$CSG[9200]", "y": 8 },
        { "gx": "$CSG[9582]", "y": 2 },
        { "gx": "$CSG[9208]", "y": -1 },
        { "gx": "$CSG[9583]", "y": -1 },
        { "gx": "$CSG[9216]", "y": 26 },
        { "gx": "$CSG[9584]", "y": -5 },
        { "gx": "$CSG[9224]", "y": 3 },
        { "gx": "$CSG[9585]", "y": 9 },
        { "gx": "$CSG[9197]", "y": 1 },
        { "gx": "$CSG[9446]", "y": 0 },
        { "gx": "$CSG[9447]", "y": 2 },
        { "gx": "$CSG[9448]", "y": 3 },
        { "gx": "$CSG[9205]", "y": 4 },
        { "gx": "$CSG[9449]", "y": 5 },
        { "gx": "$CSG[9450]", "y": 4 },
        { "gx": "$CSG[9451]", "y": 2 },
        { "gx": "$CSG[9213]", "y": 0 },
        { "gx": "$CSG[9452]", "y": -3 },
        { "gx": "$CSG[9453]", "y": -4 },
        { "gx": "$CSG[9454]", "y": 26 },
        { "gx": "$CSG[9221]", "y": 26 },
        { "gx": "$CSG[9455]", "y": 0 },
        { "gx": "$CSG[9456]", "y": -5 },
        { "gx": "$CSG[9457]", "y": -2 },
        { "gx": "$CSG[9201]", "y": 4 },
        { "gx": "$CSG[9458]", "y": 2 },
        { "gx": "$CSG[9459]", "y": -2 },
        { "gx": "$CSG[9460]", "y": -5 },
        { "gx": "$CSG[9209]", "y": -6 },
        { "gx": "$CSG[9461]", "y": -8 },
        { "gx": "$CSG[9462]", "y": -11 },
        { "gx": "$CSG[9463]", "y": -4 },
        { "gx": "$CSG[9217]", "y": 26 },
        { "gx": "$CSG[9464]", "y": -12 },
        { "gx": "$CSG[9465]", "y": -9 },
        { "gx": "$CSG[9466]", "y": -5 },
        { "gx": "$CSG[9225]", "y": -1 },
        { "gx": "$CSG[9467]", "y": 2 },
        { "gx": "$CSG[9468]", "y": 5 },
        { "gx": "$CSG[9469]", "y": 5 },
        "$CSG[8786]",
        "$CSG[8790]",
        "$CSG[8778]",
        "$CSG[8782]",
        { "gx": "$CSG[9558]", "y": 9 },
        { "gx": "$CSG[9559]", "y": 7 },
        { "gx": "$CSG[9560]", "y": 12 },
        { "gx": "$CSG[9561]", "y": 15 },
        { "gx": "$CSG[9574]", "y": 10 },
        { "gx": "$CSG[9575]", "y": 7 },
        { "gx": "$CSG[9576]", "y": 9 },
        { "gx": "$CSG[9577]", "y": 11 },
        { "gx": "$CSG[9562]", "y": 8 },
        { "gx": "$CSG[9563]", "y": 7 },
        { "gx": "$CSG[9564]", "y": 26 },
        { "gx": "$CSG[9565]", "y": 15 },
        { "gx": "$CSG[9578]", "y": 8 },
        { "gx": "$CSG[9579]", "y": 6 },
        { "gx": "$CSG[9580]", "y": 6 },
        { "gx": "$CSG[9581]", "y": 11 },
        { "gx": "$CSG[9570]", "y": 3 },
        { "gx": "$CSG[9571]", "y": 6 },
        { "gx": "$CSG[9572]", "y": 1 },
        { "gx": "$CSG[9573]", "y": -3 },
        { "gx": "$CSG[9586]", "y": 0 },
        { "gx": "$CSG[9587]", "y": -9 },
        { "gx": "$CSG[9588]", "y": -7 },
        { "gx": "$CSG[9589]", "y": 7 },
        { "gx": "$CSG[9258]", "y": 5 },
        { "gx": "$CSG[9606]", "y": 7 },
        { "gx": "$CSG[9259]", "y": 6 },
        { "gx": "$CSG[9607]", "y": 1 },
        { "gx": "$CSG[9260]", "y": -2 },
        { "gx": "$CSG[9608]", "y": 26 },
        { "gx": "$CSG[9261]", "y": 3 },
        { "gx": "$CSG[9609]", "y": 0 },
        { "gx": "$CSG[9262]", "y": 11 },
        { "gx": "$CSG[9610]", "y": 12 },
        { "gx": "$CSG[9263]", "y": 12 },
        { "gx": "$CSG[9611]", "y": 10 },
        { "gx": "$CSG[9264]", "y": 7 },
        { "gx": "$CSG[9612]", "y": 7 },
        { "gx": "$CSG[9265]", "y": 10 },
        { "gx": "$CSG[9613]", "y": 14 },
        { "gx": "$CSG[9226]", "y": 1 },
        { "gx": "$CSG[9227]", "y": 3 },
        { "gx": "$CSG[9228]", "y": 4 },
        { "gx": "$CSG[9229]", "y": 3 },
        { "gx": "$CSG[9230]", "y": 1 },
        { "gx": "$CSG[9231]", "y": -3 },
        { "gx": "$CSG[9232]", "y": -6 },
        { "gx": "$CSG[9233]", "y": -8 },
        { "gx": "$CSG[9234]", "y": -10 },
        { "gx": "$CSG[9235]", "y": -12 },
        { "gx": "$CSG[9236]", "y": -12 },
        { "gx": "$CSG[9237]", "y": -11 },
        { "gx": "$CSG[9238]", "y": -9 },
        { "gx": "$CSG[9239]", "y": -7 },
        { "gx": "$CSG[9240]", "y": -4 },
        { "gx": "$CSG[9241]", "y": -2 },
        { "gx": "$CSG[9242]", "y": 9 },
        { "gx": "$CSG[9243]", "y": 11 },
        { "gx": "$CSG[9244]", "y": 11 },
        { "gx": "$CSG[9245]", "y": 12 },
        { "gx": "$CSG[9246]", "y": 12 },
        { "gx": "$CSG[9247]", "y": 9 },
        { "gx": "$CSG[9248]", "y": 7 },
        { "gx": "$CSG[9249]", "y": 5 },
        { "gx": "$CSG[9250]", "y": 6 },
        { "gx": "$CSG[9251]", "y": 8 },
        { "gx": "$CSG[9252]", "y": 7 },
        { "gx": "$CSG[9253]", "y": 8 },
        { "gx": "$CSG[9254]", "y": 11 },
        { "gx": "$CSG[9255]", "y": 10 },
        { "gx": "$CSG[9256]", "y": 13 },
        { "gx": "$CSG[9257]", "y": 12 },
        { "gx": "$CSG[9266]", "y": 5 },
        { "gx": "$CSG[9267]", "y": 6 },
        { "gx": "$CSG[9268]", "y": -2 },
        { "gx": "$CSG[9269]", "y": 4 },
        { "gx": "$CSG[9270]", "y": 9 },
        { "gx": "$CSG[9271]", "y": 9 },
        { "gx": "$CSG[9272]", "y": 7 },
        { "gx": "$CSG[9273]", "y": 14 },
        { "gx": "$CSG[9274]", "y": 6 },
        { "gx": "$CSG[9275]", "y": 4 },
        { "gx": "$CSG[9276]", "y": -5 },
        { "gx": "$CSG[9277]", "y": 2 },
        { "gx": "$CSG[9278]", "y": 11 },
        { "gx": "$CSG[9279]", "y": 9 },
        { "gx": "$CSG[9280]", "y": 8 },
        { "gx": "$CSG[9281]", "y": 13 },
        { "gx": "$CSG[9590]", "y": 7 },
        { "gx": "$CSG[9591]", "y": 2 },
        { "gx": "$CSG[9592]", "y": 26 },
        { "gx": "$CSG[9593]", "y": 0 },
        { "gx": "$CSG[9594]", "y": 11 },
        { "gx": "$CSG[9595]", "y": 9 },
        { "gx": "$CSG[9596]", "y": 7 },
        { "gx": "$CSG[9597]", "y": 15 },
        { "gx": "$CSG[9598]", "y": 8 },
        { "gx": "$CSG[9599]", "y": -1 },
        { "gx": "$CSG[9600]", "y": 26 },
        { "gx": "$CSG[9601]", "y": 4 },
        { "gx": "$CSG[9602]", "y": 11 },
        { "gx": "$CSG[9603]", "y": 9 },
        { "gx": "$CSG[9604]", "y": 8 },
        { "gx": "$CSG[9605]", "y": -5 }
    ],
    "noCsgImages": [
        { "path": "images/preview.png", "format": "raw" },
        "",
        "",
        "$RCT2:OBJDATA/VEKST.DAT[3]",
        "$RCT2:OBJDATA/VEKST.DAT[5]",
        "$RCT2:OBJDATA/VEKST.DAT[7]",
        "$RCT2:OBJDATA/VEKST.DAT[9]",
        "$RCT2:OBJDATA/VEKST.DAT[11]",
        "$RCT2:OBJDATA/VEKST.DAT[13]",
        "$RCT2:OBJDATA/VEKST.DAT[15]",
        "$RCT2:OBJDATA/VEKST.DAT[17]",
        "$RCT2:OBJDATA/VEKST.DAT[19]",
        "$RCT2:OBJDATA/VEKST.DAT[21]",
        "$RCT2:OBJDATA/VEKST.DAT[23]",
        "$RCT2:OBJDATA/VEKST.DAT[25]",
        "$RCT2:OBJDATA/VEKST.DAT[27]",
        "$RCT2:OBJDATA/VEKST.DAT[29]",
        "$RCT2:OBJDATA/VEKST.DAT[31]",
        "$RCT2:OBJDATA/VEKST.DAT[33]",
        "$RCT2:OBJDATA/VEKST.DAT[35..42]",
        "$RCT2:OBJDATA/VEKST.DAT[43]",
        "$RCT2:OBJDATA/VEKST.DAT[45]",
        "$RCT2:OBJDATA/VEKST.DAT[47]",
        "$RCT2:OBJDATA/VEKST.DAT[49]",
        "$RCT2:OBJDATA/VEKST.DAT[51]",
        "$RCT2:OBJDATA/VEKST.DAT[53]",
        "$RCT2:OBJDATA/VEKST.DAT[55]",
        "$RCT2:OBJDATA/VEKST.DAT[57]",
        "$RCT2:OBJDATA/VEKST.DAT[59]",
        "$RCT2:OBJDATA/VEKST.DAT[61]",
        "$RCT2:OBJDATA/VEKST.DAT[63]",
        "$RCT2:OBJDATA/VEKST.DAT[65]",
        "$RCT2:OBJDATA/VEKST.DAT[67]",
        "$RCT2:OBJDATA/VEKST.DAT[69]",
        "$RCT2:OBJDATA/VEKST.DAT[71]",
        "$RCT2:OBJDATA/VEKST.DAT[73]",
        "$RCT2:OBJDATA/VEKST.DAT[75]",
        "$RCT2:OBJDATA/VEKST.DAT[77]",
        "$RCT2:OBJDATA/VEKST.DAT[79]",
        "$RCT2:OBJDATA/VEKST.DAT[81]",
        "$RCT2:OBJDATA/VEKST.DAT[83]",
        "$RCT2:OBJDATA/VEKST.DAT[85]",
        "$RCT2:OBJDATA/VEKST.DAT[87]",
        "$RCT2:OBJDATA/VEKST.DAT[89]",
        "$RCT2:OBJDATA/VEKST.DAT[91]",
        "$RCT2:OBJDATA/VEKST.DAT[93]",
        "$RCT2:OBJDATA/VEKST.DAT[95]",
        "$RCT2:OBJDATA/VEKST.DAT[97]",
        "$RCT2:OBJDATA/VEKST.DAT[99]",
        "$RCT2:OBJDATA/VEKST.DAT[101]",
        "$RCT2:OBJDATA/VEKST.DAT[103]",
        "$RCT2:OBJDATA/VEKST.DAT[105]",
        "$RCT2:OBJDATA/VEKST.DAT[107..122]",
        "$RCT2:OBJDATA/VEKST.DAT[123]",
        "$RCT2:OBJDATA/VEKST.DAT[125]",
        "$RCT2:OBJDATA/VEKST.DAT[127]",
        "$RCT2:OBJDATA/VEKST.DAT[129]",
        "$RCT2:OBJDATA/VEKST.DAT[131]",
        "$RCT2:OBJDATA/VEKST.DAT[133]",
        "$RCT2:OBJDATA/VEKST.DAT[135]",
        "$RCT2:OBJDATA/VEKST.DAT[137]",
        "$RCT2:OBJDATA/VEKST.DAT[139]",
        "$RCT2:OBJDATA/VEKST.DAT[141]",
        "$RCT2:OBJDATA/VEKST.DAT[143]",
        "$RCT2:OBJDATA/VEKST.DAT[145]",
        "$RCT2:OBJDATA/VEKST.DAT[147]",
        "$RCT2:OBJDATA/VEKST.DAT[149]",
        "$RCT2:OBJDATA/VEKST.DAT[151]",
        "$RCT2:OBJDATA/VEKST.DAT[153]",
        "$RCT2:OBJDATA/VEKST.DAT[155]",
        "$RCT2:OBJDATA/VEKST.DAT[157]",
        "$RCT2:OBJDATA/VEKST.DAT[159]",
        "$RCT2:OBJDATA/VEKST.DAT[161]",
        "$RCT2:OBJDATA/VEKST.DAT[163]",
        "$RCT2:OBJDATA/VEKST.DAT[165]",
        "$RCT2:OBJDATA/VEKST.DAT[167]",
        "$RCT2:OBJDATA/VEKST.DAT[169]",
        "$RCT2:OBJDATA/VEKST.DAT[171]",
        "$RCT2:OBJDATA/VEKST.DAT[173]",
        "$RCT2:OBJDATA/VEKST.DAT[175]",
        "$RCT2:OBJDATA/VEKST.DAT[177]",
        "$RCT2:OBJDATA/VEKST.DAT[179]",
        "$RCT2:OBJDATA/VEKST.DAT[181]",
        "$RCT2:OBJDATA/VEKST.DAT[183]",
        "$RCT2:OBJDATA/VEKST.DAT[185]",
        "$RCT2:OBJDATA/VEKST.DAT[187..194]",
        "$RCT2:OBJDATA/VEKST.DAT[195]",
        "$RCT2:OBJDATA/VEKST.DAT[203]",
        "$RCT2:OBJDATA/VEKST.DAT[211]",
        "$RCT2:OBJDATA/VEKST.DAT[219]",
        "$RCT2:OBJDATA/VEKST.DAT[227]",
        "$RCT2:OBJDATA/VEKST.DAT[235]",
        "$RCT2:OBJDATA/VEKST.DAT[243]",
        "$RCT2:OBJDATA/VEKST.DAT[251]",
        "$RCT2:OBJDATA/VEKST.DAT[259..342]",
        "$RCT2:OBJDATA/VEKST.DAT[343]",
        "$RCT2:OBJDATA/VEKST.DAT[345]",
        "$RCT2:OBJDATA/VEKST.DAT[347]",
        "$RCT2:OBJDATA/VEKST.DAT[349]",
        "$RCT2:OBJDATA/VEKST.DAT[351]",
        "$RCT2:OBJDATA/VEKST.DAT[353]",
        "$RCT2:OBJDATA/VEKST.DAT[355]",
        "$RCT2:OBJDATA/VEKST.DAT[357]",
        "$RCT2:OBJDATA/VEKST.DAT[359]",
        "$RCT2:OBJDATA/VEKST.DAT[361]",
        "$RCT2:OBJDATA/VEKST.DAT[363]",
        "$RCT2:OBJDATA/VEKST.DAT[365]",
        "$RCT2:OBJDATA/VEKST.DAT[367]",
        "$RCT2:OBJDATA/VEKST.DAT[369]",
        "$RCT2:OBJDATA/VEKST.DAT[371]",
        "$RCT2:OBJDATA/VEKST.DAT[373]",
        "$RCT2:OBJDATA/VEKST.DAT[375]",
        "$RCT2:OBJDATA/VEKST.DAT[377]",
        "$RCT2:OBJDATA/VEKST.DAT[379]",
        "$RCT2:OBJDATA/VEKST.DAT[381]",
        "$RCT2:OBJDATA/VEKST.DAT[383]",
        "$RCT2:OBJDATA/VEKST.DAT[385]",
        "$RCT2:OBJDATA/VEKST.DAT[387]",
        "$RCT2:OBJDATA/VEKST.DAT[389]",
        "$RCT2:OBJDATA/VEKST.DAT[391]",
        "$RCT2:OBJDATA/VEKST.DAT[393]",
        "$RCT2:OBJDATA/VEKST.DAT[395]",
        "$RCT2:OBJDATA/VEKST.DAT[397]",
        "$RCT2:OBJDATA/VEKST.DAT[399]",
        "$RCT2:OBJDATA/VEKST.DAT[401]",
        "$RCT2:OBJDATA/VEKST.DAT[403]",
        "$RCT2:OBJDATA/VEKST.DAT[405]",
        "$RCT2:OBJDATA/VEKST.DAT[407..446]",
        "$RCT2:OBJDATA/VEKST.DAT[447]",
        "$RCT2:OBJDATA/VEKST.DAT[455]",
        "$RCT2:OBJDATA/VEKST.DAT[463]",
        "$RCT2:OBJDATA/VEKST.DAT[471]",
        "$RCT2:OBJDATA/VEKST.DAT[479]",
        "$RCT2:OBJDATA/VEKST.DAT[487]",
        "$RCT2:OBJDATA/VEKST.DAT[495]",
        "$RCT2:OBJDATA/VEKST.DAT[503]",
        "$RCT2:OBJDATA/VEKST.DAT[511]",
        "$RCT2:OBJDATA/VEKST.DAT[519]",
        "$RCT2:OBJDATA/VEKST.DAT[527]",
        "$RCT2:OBJDATA/VEKST.DAT[535]",
        "$RCT2:OBJDATA/VEKST.DAT[543]",
        "$RCT2:OBJDATA/VEKST.DAT[551]",
        "$RCT2:OBJDATA/VEKST.DAT[559]",
        "$RCT2:OBJDATA/VEKST.DAT[567]",
        "$RCT2:OBJDATA/VEKST.DAT[575..682]",
        "$RCT2:OBJDATA/VEKST.DAT[683]",
        "$RCT2:OBJDATA/VEKST.DAT[685]",
        "$RCT2:OBJDATA/VEKST.DAT[687]",
        "$RCT2:OBJDATA/VEKST.DAT[689]",
        "$RCT2:OBJDATA/VEKST.DAT[691]",
        "$RCT2:OBJDATA/VEKST.DAT[693]",
        "$RCT2:OBJDATA/VEKST.DAT[695]",
        "$RCT2:OBJDATA/VEKST.DAT[697]",
        "$RCT2:OBJDATA/VEKST.DAT[699]",
        "$RCT2:OBJDATA/VEKST.DAT[701]",
        "$RCT2:OBJDATA/VEKST.DAT[703]",
        "$RCT2:OBJDATA/VEKST.DAT[705]",
        "$RCT2:OBJDATA/VEKST.DAT[707]",
        "$RCT2:OBJDATA/VEKST.DAT[709]",
        "$RCT2:OBJDATA/VEKST.DAT[711]",
        "$RCT2:OBJDATA/VEKST.DAT[713]",
        "$RCT2:OBJDATA/VEKST.DAT[715..722]",
        "$RCT2:OBJDATA/VEKST.DAT[723]",
        "$RCT2:OBJDATA/VEKST.DAT[725]",
        "$RCT2:OBJDATA/VEKST.DAT[727]",
        "$RCT2:OBJDATA/VEKST.DAT[729]",
        "$RCT2:OBJDATA/VEKST.DAT[731]",
        "$RCT2:OBJDATA/VEKST.DAT[733]",
        "$RCT2:OBJDATA/VEKST.DAT[735]",
        "$RCT2:OBJDATA/VEKST.DAT[737]",
        "$RCT2:OBJDATA/VEKST.DAT[739]",
        "$RCT2:OBJDATA/VEKST.DAT[741]",
        "$RCT2:OBJDATA/VEKST.DAT[743]",
        "$RCT2:OBJDATA/VEKST.DAT[745]",
        "$RCT2:OBJDATA/VEKST.DAT[747]",
        "$RCT2:OBJDATA/VEKST.DAT[749]",
        "$RCT2:OBJDATA/VEKST.DAT[751]",
        "$RCT2:OBJDATA/VEKST.DAT[753]",
        "$RCT2:OBJDATA/VEKST.DAT[755]",
        "$RCT2:OBJDATA/VEKST.DAT[757]",
        "$RCT2:OBJDATA/VEKST.DAT[759]",
        "$RCT2:OBJDATA/VEKST.DAT[761]",
        "$RCT2:OBJDATA/VEKST.DAT[763]",
        "$RCT2:OBJDATA/VEKST.DAT[765]",
        "$RCT2:OBJDATA/VEKST.DAT[767]",
        "$RCT2:OBJDATA/VEKST.DAT[769]",
        "$RCT2:OBJDATA/VEKST.DAT[771]",
        "$RCT2:OBJDATA/VEKST.DAT[773]",
        "$RCT2:OBJDATA/VEKST.DAT[775]",
        "$RCT2:OBJDATA/VEKST.DAT[777]",
        "$RCT2:OBJDATA/VEKST.DAT[779]",
        "$RCT2:OBJDATA/VEKST.DAT[781]",
        "$RCT2:OBJDATA/VEKST.DAT[783]",
        "$RCT2:OBJDATA/VEKST.DAT[785]",
        "$RCT2:OBJDATA/VEKST.DAT[787..802]",
        "$RCT2:OBJDATA/VEKST.DAT[803]",
        "$RCT2:OBJDATA/VEKST.DAT[805]",
        "$RCT2:OBJDATA/VEKST.DAT[807]",
        "$RCT2:OBJDATA/VEKST.DAT[809]",
        "$RCT2:OBJDATA/VEKST.DAT[811]",
        "$RCT2:OBJDATA/VEKST.DAT[813]",
        "$RCT2:OBJDATA/VEKST.DAT[815]",
        "$RCT2:OBJDATA/VEKST.DAT[817]",
        "$RCT2:OBJDATA/VEKST.DAT[819]",
        "$RCT2:OBJDATA/VEKST.DAT[821]",
        "$RCT2:OBJDATA/VEKST.DAT[823]",
        "$RCT2:OBJDATA/VEKST.DAT[825]",
        "$RCT2:OBJDATA/VEKST.DAT[827]",
        "$RCT2:OBJDATA/VEKST.DAT[829]",
        "$RCT2:OBJDATA/VEKST.DAT[831]",
        "$RCT2:OBJDATA/VEKST.DAT[833]",
        "$RCT2:OBJDATA/VEKST.DAT[835]",
        "$RCT2:OBJDATA/VEKST.DAT[837]",
        "$RCT2:OBJDATA/VEKST.DAT[839]",
        "$RCT2:OBJDATA/VEKST.DAT[841]",
        "$RCT2:OBJDATA/VEKST.DAT[843]",
        "$RCT2:OBJDATA/VEKST.DAT[845]",
        "$RCT2:OBJDATA/VEKST.DAT[847]",
        "$RCT2:OBJDATA/VEKST.DAT[849]",
        "$RCT2:OBJDATA/VEKST.DAT[851]",
        "$RCT2:OBJDATA/VEKST.DAT[853]",
        "$RCT2:OBJDATA/VEKST.DAT[855]",
        "$RCT2:OBJDATA/VEKST.DAT[857]",
        "$RCT2:OBJDATA/VEKST.DAT[859]",
        "$RCT2:OBJDATA/VEKST.DAT[861]",
        "$RCT2:OBJDATA/VEKST.DAT[863]",
        "$RCT2:OBJDATA/VEKST.DAT[865]",
        "$RCT2:OBJDATA/VEKST.DAT[867..874]",
        "$RCT2:OBJDATA/VEKST.DAT[875]",
        "$RCT2:OBJDATA/VEKST.DAT[883]",
        "$RCT2:OBJDATA/VEKST.DAT[891]",
        "$RCT2:OBJDATA/VEKST.DAT[899]",
        "$RCT2:OBJDATA/VEKST.DAT[907]",
        "$RCT2:OBJDATA/VEKST.DAT[915]",
        "$RCT2:OBJDATA/VEKST.DAT[923]",
        "$RCT2:OBJDATA/VEKST.DAT[931]",
        "$RCT2:OBJDATA/VEKST.DAT[939..1022]",
        "$RCT2:OBJDATA/VEKST.DAT[1023]",
        "$RCT2:OBJDATA/VEKST.DAT[1025]",
        "$RCT2:OBJDATA/VEKST.DAT[1027]",
        "$RCT2:OBJDATA/VEKST.DAT[1029]",
        "$RCT2:OBJDATA/VEKST.DAT[1031]",
        "$RCT2:OBJDATA/VEKST.DAT[1033]",
        "$RCT2:OBJDATA/VEKST.DAT[1035]",
        "$RCT2:OBJDATA/VEKST.DAT[1037]",
        "$RCT2:OBJDATA/VEKST.DAT[1039]",
        "$RCT2:OBJDATA/VEKST.DAT[1041]",
        "$RCT2:OBJDATA/VEKST.DAT[1043]",
        "$RCT2:OBJDATA/VEKST.DAT[1045]",
        "$RCT2:OBJDATA/VEKST.DAT[1047]",
        "$RCT2:OBJDATA/VEKST.DAT[1049]",
        "$RCT2:OBJDATA/VEKST.DAT[1051]",
        "$RCT2:OBJDATA/VEKST.DAT[1053]",
        "$RCT2:OBJDATA/VEKST.DAT[1055]",
        "$RCT2:OBJDATA/VEKST.DAT[1057]",
        "$RCT2:OBJDATA/VEKST.DAT[1059]",
        "$RCT2:OBJDATA/VEKST.DAT[1061]",
        "$RCT2:OBJDATA/VEKST.DAT[1063]",
        "$RCT2:OBJDATA/VEKST.DAT[1065]",
        "$RCT2:OBJDATA/VEKST.DAT[1067]",
        "$RCT2:OBJDATA/VEKST.DAT[1069]",
        "$RCT2:OBJDATA/VEKST.DAT[1071]",
        "$RCT2:OBJDATA/VEKST.DAT[1073]",
        "$RCT2:OBJDATA/VEKST.DAT[1075]",
        "$RCT2:OBJDATA/VEKST.DAT[1077]",
        "$RCT2:OBJDATA/VEKST.DAT[1079]",
        "$RCT2:OBJDATA/VEKST.DAT[1081]",
        "$RCT2:OBJDATA/VEKST.DAT[1083]",
        "$RCT2:OBJDATA/VEKST.DAT[1085]",
        "$RCT2:OBJDATA/VEKST.DAT[1087..1126]",
        "$RCT2:OBJDATA/VEKST.DAT[1127]",
        "$RCT2:OBJDATA/VEKST.DAT[1135]",
        "$RCT2:OBJDATA/VEKST.DAT[1143]",
        "$RCT2:OBJDATA/VEKST.DAT[1151]",
        "$RCT2:OBJDATA/VEKST.DAT[1159]",
        "$RCT2:OBJDATA/VEKST.DAT[1167]",
        "$RCT2:OBJDATA/VEKST.DAT[1175]",
        "$RCT2:OBJDATA/VEKST.DAT[1183]",
        "$RCT2:OBJDATA/VEKST.DAT[1191]",
        "$RCT2:OBJDATA/VEKST.DAT[1199]",
        "$RCT2:OBJDATA/VEKST.DAT[1207]",
        "$RCT2:OBJDATA/VEKST.DAT[1215]",
        "$RCT2:OBJDATA/VEKST.DAT[1223]",
        "$RCT2:OBJDATA/VEKST.DAT[1231]",
        "$RCT2:OBJDATA/VEKST.DAT[1239]",
        "$RCT2:OBJDATA/VEKST.DAT[1247]",
        "$RCT2:OBJDATA/VEKST.DAT[1255..1362]",
        "$RCT2:OBJDATA/VEKST.DAT[1363]",
        "$RCT2:OBJDATA/VEKST.DAT[1365]",
        "$RCT2:OBJDATA/VEKST.DAT[1367]",
        "$RCT2:OBJDATA/VEKST.DAT[1369]",
        "$RCT2:OBJDATA/VEKST.DAT[1371]",
        "$RCT2:OBJDATA/VEKST.DAT[1373]",
        "$RCT2:OBJDATA/VEKST.DAT[1375]",
        "$RCT2:OBJDATA/VEKST.DAT[1377]",
        "$RCT2:OBJDATA/VEKST.DAT[1379]",
        "$RCT2:OBJDATA/VEKST.DAT[1381]",
        "$RCT2:OBJDATA/VEKST.DAT[1383]",
        "$RCT2:OBJDATA/VEKST.DAT[1385]",
        "$RCT2:OBJDATA/VEKST.DAT[1387]",
        "$RCT2:OBJDATA/VEKST.DAT[1389]",
        "$RCT2:OBJDATA/VEKST.DAT[1391]",
        "$RCT2:OBJDATA/VEKST.DAT[1393]",
        "$RCT2:OBJDATA/VEKST.DAT[1395..1402]",
        "$RCT2:OBJDATA/VEKST.DAT[1403]",
        "$RCT2:OBJDATA/VEKST.DAT[1405]",
        "$RCT2:OBJDATA/VEKST.DAT[1407]",
        "$RCT2:OBJDATA/VEKST.DAT[1409]",
        "$RCT2:OBJDATA/VEKST.DAT[1411]",
        "$RCT2:OBJDATA/VEKST.DAT[1413]",
        "$RCT2:OBJDATA/VEKST.DAT[1415]",
        "$RCT2:OBJDATA/VEKST.DAT[1417]",
        "$RCT2:OBJDATA/VEKST.DAT[1419]",
        "$RCT2:OBJDATA/VEKST.DAT[1421]",
        "$RCT2:OBJDATA/VEKST.DAT[1423]",
        "$RCT2:OBJDATA/VEKST.DAT[1425]",
        "$RCT2:OBJDATA/VEKST.DAT[1427]",
        "$RCT2:OBJDATA/VEKST.DAT[1429]",
        "$RCT2:OBJDATA/VEKST.DAT[1431]",
        "$RCT2:OBJDATA/VEKST.DAT[1433]",
        "$RCT2:OBJDATA/VEKST.DAT[1435]",
        "$RCT2:OBJDATA/VEKST.DAT[1437]",
        "$RCT2:OBJDATA/VEKST.DAT[1439]",
        "$RCT2:OBJDATA/VEKST.DAT[1441]",
        "$RCT2:OBJDATA/VEKST.DAT[1443]",
        "$RCT2:OBJDATA/VEKST.DAT[1445]",
        "$RCT2:OBJDATA/VEKST.DAT[1447]",
        "$RCT2:OBJDATA/VEKST.DAT[1449]",
        "$RCT2:OBJDATA/VEKST.DAT[1451]",
        "$RCT2:OBJDATA/VEKST.DAT[1453]",
        "$RCT2:OBJDATA/VEKST.DAT[1455]",
        "$RCT2:OBJDATA/VEKST.DAT[1457]",
        "$RCT2:OBJDATA/VEKST.DAT[1459]",
        "$RCT2:OBJDATA/VEKST.DAT[1461]",
        "$RCT2:OBJDATA/VEKST.DAT[1463]",
        "$RCT2:OBJDATA/VEKST.DAT[1465]",
        "$RCT2:OBJDATA/VEKST.DAT[1467..1482]",
        "$RCT2:OBJDATA/VEKST.DAT[1483]",
        "$RCT2:OBJDATA/VEKST.DAT[1485]",
        "$RCT2:OBJDATA/VEKST.DAT[1487]",
        "$RCT2:OBJDATA/VEKST.DAT[1489]",
        "$RCT2:OBJDATA/VEKST.DAT[1491]",
        "$RCT2:OBJDATA/VEKST.DAT[1493]",
        "$RCT2:OBJDATA/VEKST.DAT[1495]",
        "$RCT2:OBJDATA/VEKST.DAT[1497]",
        "$RCT2:OBJDATA/VEKST.DAT[1499]",
        "$RCT2:OBJDATA/VEKST.DAT[1501]",
        "$RCT2:OBJDATA/VEKST.DAT[1503]",
        "$RCT2:OBJDATA/VEKST.DAT[1505]",
        "$RCT2:OBJDATA/VEKST.DAT[1507]",
        "$RCT2:OBJDATA/VEKST.DAT[1509]",
        "$RCT2:OBJDATA/VEKST.DAT[1511]",
        "$RCT2:OBJDATA/VEKST.DAT[1513]",
        "$RCT2:OBJDATA/VEKST.DAT[1515]",
        "$RCT2:OBJDATA/VEKST.DAT[1517]",
        "$RCT2:OBJDATA/VEKST.DAT[1519]",
        "$RCT2:OBJDATA/VEKST.DAT[1521]",
        "$RCT2:OBJDATA/VEKST.DAT[1523]",
        "$RCT2:OBJDATA/VEKST.DAT[1525]",
        "$RCT2:OBJDATA/VEKST.DAT[1527]",
        "$RCT2:OBJDATA/VEKST.DAT[1529]",
        "$RCT2:OBJDATA/VEKST.DAT[1531]",
        "$RCT2:OBJDATA/VEKST.DAT[1533]",
        "$RCT2:OBJDATA/VEKST.DAT[1535]",
        "$RCT2:OBJDATA/VEKST.DAT[1537]",
        "$RCT2:OBJDATA/VEKST.DAT[1539]",
        "$RCT2:OBJDATA/VEKST.DAT[1541]",
        "$RCT2:OBJDATA/VEKST.DAT[1543]",
        "$RCT2:OBJDATA/VEKST.DAT[1545]",
        "$RCT2:OBJDATA/VEKST.DAT[1547..1554]",
        "$RCT2:OBJDATA/VEKST.DAT[1555]",
        "$RCT2:OBJDATA/VEKST.DAT[1563]",
        "$RCT2:OBJDATA/VEKST.DAT[1571]",
        "$RCT2:OBJDATA/VEKST.DAT[1579]",
        "$RCT2:OBJDATA/VEKST.DAT[1587]",
        "$RCT2:OBJDATA/VEKST.DAT[1595]",
        "$RCT2:OBJDATA/VEKST.DAT[1603]",
        "$RCT2:OBJDATA/VEKST.DAT[1611]",
        "$RCT2:OBJDATA/VEKST.DAT[1619..1702]",
        "$RCT2:OBJDATA/VEKST.DAT[1703]",
        "$RCT2:OBJDATA/VEKST.DAT[1705]",
        "$RCT2:OBJDATA/VEKST.DAT[1707]",
        "$RCT2:OBJDATA/VEKST.DAT[1709]",
        "$RCT2:OBJDATA/VEKST.DAT[1711]",
        "$RCT2:OBJDATA/VEKST.DAT[1713]",
        "$RCT2:OBJDATA/VEKST.DAT[1715]",
        "$RCT2:OBJDATA/VEKST.DAT[1717]",
        "$RCT2:OBJDATA/VEKST.DAT[1719]",
        "$RCT2:OBJDATA/VEKST.DAT[1721]",
        "$RCT2:OBJDATA/VEKST.DAT[1723]",
        "$RCT2:OBJDATA/VEKST.DAT[1725]",
        "$RCT2:OBJDATA/VEKST.DAT[1727]",
        "$RCT2:OBJDATA/VEKST.DAT[1729]",
        "$RCT2:OBJDATA/VEKST.DAT[1731]",
        "$RCT2:OBJDATA/VEKST.DAT[1733]",
        "$RCT2:OBJDATA/VEKST.DAT[1735]",
        "$RCT2:OBJDATA/VEKST.DAT[1737]",
        "$RCT2:OBJDATA/VEKST.DAT[1739]",
        "$RCT2:OBJDATA/VEKST.DAT[1741]",
        "$RCT2:OBJDATA/VEKST.DAT[1743]",
        "$RCT2:OBJDATA/VEKST.DAT[1745]",
        "$RCT2:OBJDATA/VEKST.DAT[1747]",
        "$RCT2:OBJDATA/VEKST.DAT[1749]",
        "$RCT2:OBJDATA/VEKST.DAT[1751]",
        "$RCT2:OBJDATA/VEKST.DAT[1753]",
        "$RCT2:OBJDATA/VEKST.DAT[1755]",
        "$RCT2:OBJDATA/VEKST.DAT[1757]",
        "$RCT2:OBJDATA/VEKST.DAT[1759]",
        "$RCT2:OBJDATA/VEKST.DAT[1761]",
        "$RCT2:OBJDATA/VEKST.DAT[1763]",
        "$RCT2:OBJDATA/VEKST.DAT[1765]",
        "$RCT2:OBJDATA/VEKST.DAT[1767..1806]",
        "$RCT2:OBJDATA/VEKST.DAT[1807]",
        "$RCT2:OBJDATA/VEKST.DAT[1815]",
        "$RCT2:OBJDATA/VEKST.DAT[1823]",
        "$RCT2:OBJDATA/VEKST.DAT[1831]",
        "$RCT2:OBJDATA/VEKST.DAT[1839]",
        "$RCT2:OBJDATA/VEKST.DAT[1847]",
        "$RCT2:OBJDATA/VEKST.DAT[1855]",
        "$RCT2:OBJDATA/VEKST.DAT[1863]",
        "$RCT2:OBJDATA/VEKST.DAT[1871]",
        "$RCT2:OBJDATA/VEKST.DAT[1879]",
        "$RCT2:OBJDATA/VEKST.DAT[1887]",
        "$RCT2:OBJDATA/VEKST.DAT[1895]",
        "$RCT2:OBJDATA/VEKST.DAT[1903]",
        "$RCT2:OBJDATA/VEKST.DAT[1911]",
        "$RCT2:OBJDATA/VEKST.DAT[1919]",
        "$RCT2:OBJDATA/VEKST.DAT[1927]",
        "$RCT2:OBJDATA/VEKST.DAT[1935..2042]",
        "$RCT2:OBJDATA/VEKST.DAT[2043]",
        "$RCT2:OBJDATA/VEKST.DAT[2045]",
        "$RCT2:OBJDATA/VEKST.DAT[2047]",
        "$RCT2:OBJDATA/VEKST.DAT[2049]",
        "$RCT2:OBJDATA/VEKST.DAT[2051]",
        "$RCT2:OBJDATA/VEKST.DAT[2053]",
        "$RCT2:OBJDATA/VEKST.DAT[2055]",
        "$RCT2:OBJDATA/VEKST.DAT[2057]",
        "$RCT2:OBJDATA/VEKST.DAT[2059]",
        "$RCT2:OBJDATA/VEKST.DAT[2061]",
        "$RCT2:OBJDATA/VEKST.DAT[2063]",
        "$RCT2:OBJDATA/VEKST.DAT[2065]",
        "$RCT2:OBJDATA/VEKST.DAT[2067]",
        "$RCT2:OBJDATA/VEKST.DAT[2069]",
        "$RCT2:OBJDATA/VEKST.DAT[2071]",
        "$RCT2:OBJDATA/VEKST.DAT[2073]",
        "$RCT2:OBJDATA/VEKST.DAT[2075..2082]",
        "$RCT2:OBJDATA/VEKST.DAT[2083]",
        "$RCT2:OBJDATA/VEKST.DAT[2085]",
        "$RCT2:OBJDATA/VEKST.DAT[2087]",
        "$RCT2:OBJDATA/VEKST.DAT[2089]",
        "$RCT2:OBJDATA/VEKST.DAT[2091]",
        "$RCT2:OBJDATA/VEKST.DAT[2093]",
        "$RCT2:OBJDATA/VEKST.DAT[2095]",
        "$RCT2:OBJDATA/VEKST.DAT[2097]",
        "$RCT2:OBJDATA/VEKST.DAT[2099]",
        "$RCT2:OBJDATA/VEKST.DAT[2101]",
        "$RCT2:OBJDATA/VEKST.DAT[2103]",
        "$RCT2:OBJDATA/VEKST.DAT[2105]",
        "$RCT2:OBJDATA/VEKST.DAT[2107]",
        "$RCT2:OBJDATA/VEKST.DAT[2109]",
        "$RCT2:OBJDATA/VEKST.DAT[2111]",
        "$RCT2:OBJDATA/VEKST.DAT[2113]",
        "$RCT2:OBJDATA/VEKST.DAT[2115]",
        "$RCT2:OBJDATA/VEKST.DAT[2117]",
        "$RCT2:OBJDATA/VEKST.DAT[2119]",
        "$RCT2:OBJDATA/VEKST.DAT[2121]",
        "$RCT2:OBJDATA/VEKST.DAT[2123]",
        "$RCT2:OBJDATA/VEKST.DAT[2125]",
        "$RCT2:OBJDATA/VEKST.DAT[2127]",
        "$RCT2:OBJDATA/VEKST.DAT[2129]",
        "$RCT2:OBJDATA/VEKST.DAT[2131]",
        "$RCT2:OBJDATA/VEKST.DAT[2133]",
        "$RCT2:OBJDATA/VEKST.DAT[2135]",
        "$RCT2:OBJDATA/VEKST.DAT[2137]",
        "$RCT2:OBJDATA/VEKST.DAT[2139]",
        "$RCT2:OBJDATA/VEKST.DAT[2141]",
        "$RCT2:OBJDATA/VEKST.DAT[2143]",
        "$RCT2:OBJDATA/VEKST.DAT[2145]",
        "$RCT2:OBJDATA/VEKST.DAT[2147..2162]",
        "$RCT2:OBJDATA/VEKST.DAT[2163]",
        "$RCT2:OBJDATA/VEKST.DAT[2165]",
        "$RCT2:OBJDATA/VEKST.DAT[2167]",
        "$RCT2:OBJDATA/VEKST.DAT[2169]",
        "$RCT2:OBJDATA/VEKST.DAT[2171]",
        "$RCT2:OBJDATA/VEKST.DAT[2173]",
        "$RCT2:OBJDATA/VEKST.DAT[2175]",
        "$RCT2:OBJDATA/VEKST.DAT[2177]",
        "$RCT2:OBJDATA/VEKST.DAT[2179]",
        "$RCT2:OBJDATA/VEKST.DAT[2181]",
        "$RCT2:OBJDATA/VEKST.DAT[2183]",
        "$RCT2:OBJDATA/VEKST.DAT[2185]",
        "$RCT2:OBJDATA/VEKST.DAT[2187]",
        "$RCT2:OBJDATA/VEKST.DAT[2189]",
        "$RCT2:OBJDATA/VEKST.DAT[2191]",
        "$RCT2:OBJDATA/VEKST.DAT[2193]",
        "$RCT2:OBJDATA/VEKST.DAT[2195]",
        "$RCT2:OBJDATA/VEKST.DAT[2197]",
        "$RCT2:OBJDATA/VEKST.DAT[2199]",
        "$RCT2:OBJDATA/VEKST.DAT[2201]",
        "$RCT2:OBJDATA/VEKST.DAT[2203]",
        "$RCT2:OBJDATA/VEKST.DAT[2205]",
        "$RCT2:OBJDATA/VEKST.DAT[2207]",
        "$RCT2:OBJDATA/VEKST.DAT[2209]",
        "$RCT2:OBJDATA/VEKST.DAT[2211]",
        "$RCT2:OBJDATA/VEKST.DAT[2213]",
        "$RCT2:OBJDATA/VEKST.DAT[2215]",
        "$RCT2:OBJDATA/VEKST.DAT[2217]",
        "$RCT2:OBJDATA/VEKST.DAT[2219]",
        "$RCT2:OBJDATA/VEKST.DAT[2221]",
        "$RCT2:OBJDATA/VEKST.DAT[2223]",
        "$RCT2:OBJDATA/VEKST.DAT[2225]",
        "$RCT2:OBJDATA/VEKST.DAT[2339..2382]",
        "$RCT2:OBJDATA/VEKST.DAT[2383]",
        "$RCT2:OBJDATA/VEKST.DAT[2385]",
        "$RCT2:OBJDATA/VEKST.DAT[2387]",
        "$RCT2:OBJDATA/VEKST.DAT[2389]",
        "$RCT2:OBJDATA/VEKST.DAT[2391]",
        "$RCT2:OBJDATA/VEKST.DAT[2393]",
        "$RCT2:OBJDATA/VEKST.DAT[2395]",
        "$RCT2:OBJDATA/VEKST.DAT[2397]",
        "$RCT2:OBJDATA/VEKST.DAT[2399]",
        "$RCT2:OBJDATA/VEKST.DAT[2401]",
        "$RCT2:OBJDATA/VEKST.DAT[2403]",
        "$RCT2:OBJDATA/VEKST.DAT[2405]",
        "$RCT2:OBJDATA/VEKST.DAT[2407]",
        "$RCT2:OBJDATA/VEKST.DAT[2409]",
        "$RCT2:OBJDATA/VEKST.DAT[2411]",
        "$RCT2:OBJDATA/VEKST.DAT[2413]",
        "$RCT2:OBJDATA/VEKST.DAT[2415]",
        "$RCT2:OBJDATA/VEKST.DAT[2417]",
        "$RCT2:OBJDATA/VEKST.DAT[2419]",
        "$RCT2:OBJDATA/VEKST.DAT[2421]",
        "$RCT2:OBJDATA/VEKST.DAT[2423]",
        "$RCT2:OBJDATA/VEKST.DAT[2425]",
        "$RCT2:OBJDATA/VEKST.DAT[2427]",
        "$RCT2:OBJDATA/VEKST.DAT[2429]",
        "$RCT2:OBJDATA/VEKST.DAT[2431]",
        "$RCT2:OBJDATA/VEKST.DAT[2433]",
        "$RCT2:OBJDATA/VEKST.DAT[2435]",
        "$RCT2:OBJDATA/VEKST.DAT[2437]",
        "$RCT2:OBJDATA/VEKST.DAT[2439]",
        "$RCT2:OBJDATA/VEKST.DAT[2441]",
        "$RCT2:OBJDATA/VEKST.DAT[2443]",
        "$RCT2:OBJDATA/VEKST.DAT[2445]",
        "$RCT2:OBJDATA/VEKST.DAT[2487]",
        "$RCT2:OBJDATA/VEKST.DAT[2495]",
        "$RCT2:OBJDATA/VEKST.DAT[2503]",
        "$RCT2:OBJDATA/VEKST.DAT[2511]",
        "$RCT2:OBJDATA/VEKST.DAT[2519]",
        "$RCT2:OBJDATA/VEKST.DAT[2527]",
        "$RCT2:OBJDATA/VEKST.DAT[2535]",
        "$RCT2:OBJDATA/VEKST.DAT[2543]",
        "$RCT2:OBJDATA/VEKST.DAT[2551]",
        "$RCT2:OBJDATA/VEKST.DAT[2559]",
        "$RCT2:OBJDATA/VEKST.DAT[2567]",
        "$RCT2:OBJDATA/VEKST.DAT[2575]",
        "$RCT2:OBJDATA/VEKST.DAT[2583]",
        "$RCT2:OBJDATA/VEKST.DAT[2591]",
        "$RCT2:OBJDATA/VEKST.DAT[2599]",
        "$RCT2:OBJDATA/VEKST.DAT[2607]",
        "$RCT2:OBJDATA/VEKST.DAT[2615..2630]",
        "$RCT2:OBJDATA/VEKST.DAT[2723]",
        "$RCT2:OBJDATA/VEKST.DAT[2725]",
        "$RCT2:OBJDATA/VEKST.DAT[2727]",
        "$RCT2:OBJDATA/VEKST.DAT[2729]",
        "$RCT2:OBJDATA/VEKST.DAT[2731]",
        "$RCT2:OBJDATA/VEKST.DAT[2733]",
        "$RCT2:OBJDATA/VEKST.DAT[2735]",
        "$RCT2:OBJDATA/VEKST.DAT[2737]",
        "$RCT2:OBJDATA/VEKST.DAT[2739]",
        "$RCT2:OBJDATA/VEKST.DAT[2741]",
        "$RCT2:OBJDATA/VEKST.DAT[2743]",
        "$RCT2:OBJDATA/VEKST.DAT[2745]",
        "$RCT2:OBJDATA/VEKST.DAT[2747]",
        "$RCT2:OBJDATA/VEKST.DAT[2749]",
        "$RCT2:OBJDATA/VEKST.DAT[2751]",
        "$RCT2:OBJDATA/VEKST.DAT[2753]",
        "$RCT2:OBJDATA/VEKST.DAT[2755..2762]",
        "$RCT2:OBJDATA/VEKST.DAT[2763]",
        "$RCT2:OBJDATA/VEKST.DAT[2765]",
        "$RCT2:OBJDATA/VEKST.DAT[2767]",
        "$RCT2:OBJDATA/VEKST.DAT[2769]",
        "$RCT2:OBJDATA/VEKST.DAT[2771]",
        "$RCT2:OBJDATA/VEKST.DAT[2773]",
        "$RCT2:OBJDATA/VEKST.DAT[2775]",
        "$RCT2:OBJDATA/VEKST.DAT[2777]",
        "$RCT2:OBJDATA/VEKST.DAT[2779]",
        "$RCT2:OBJDATA/VEKST.DAT[2781]",
        "$RCT2:OBJDATA/VEKST.DAT[2783]",
        "$RCT2:OBJDATA/VEKST.DAT[2785]",
        "$RCT2:OBJDATA/VEKST.DAT[2787]",
        "$RCT2:OBJDATA/VEKST.DAT[2789]",
        "$RCT2:OBJDATA/VEKST.DAT[2791]",
        "$RCT2:OBJDATA/VEKST.DAT[2793]",
        "$RCT2:OBJDATA/VEKST.DAT[2795]",
        "$RCT2:OBJDATA/VEKST.DAT[2797]",
        "$RCT2:OBJDATA/VEKST.DAT[2799]",
        "$RCT2:OBJDATA/VEKST.DAT[2801]",
        "$RCT2:OBJDATA/VEKST.DAT[2803]",
        "$RCT2:OBJDATA/VEKST.DAT[2805]",
        "$RCT2:OBJDATA/VEKST.DAT[2807]",
        "$RCT2:OBJDATA/VEKST.DAT[2809]",
        "$RCT2:OBJDATA/VEKST.DAT[2811]",
        "$RCT2:OBJDATA/VEKST.DAT[2813]",
        "$RCT2:OBJDATA/VEKST.DAT[2815]",
        "$RCT2:OBJDATA/VEKST.DAT[2817]",
        "$RCT2:OBJDATA/VEKST.DAT[2819]",
        "$RCT2:OBJDATA/VEKST.DAT[2821]",
        "$RCT2:OBJDATA/VEKST.DAT[2823]",
        "$RCT2:OBJDATA/VEKST.DAT[2825]",
        "$RCT2:OBJDATA/VEKST.DAT[2827..2842]",
        "$RCT2:OBJDATA/VEKST.DAT[2843]",
        "$RCT2:OBJDATA/VEKST.DAT[2845]",
        "$RCT2:OBJDATA/VEKST.DAT[2847]",
        "$RCT2:OBJDATA/VEKST.DAT[2849]",
        "$RCT2:OBJDATA/VEKST.DAT[2851]",
        "$RCT2:OBJDATA/VEKST.DAT[2853]",
        "$RCT2:OBJDATA/VEKST.DAT[2855]",
        "$RCT2:OBJDATA/VEKST.DAT[2857]",
        "$RCT2:OBJDATA/VEKST.DAT[2859]",
        "$RCT2:OBJDATA/VEKST.DAT[2861]",
        "$RCT2:OBJDATA/VEKST.DAT[2863]",
        "$RCT2:OBJDATA/VEKST.DAT[2865]",
        "$RCT2:OBJDATA/VEKST.DAT[2867]",
        "$RCT2:OBJDATA/VEKST.DAT[2869]",
        "$RCT2:OBJDATA/VEKST.DAT[2871]",
        "$RCT2:OBJDATA/VEKST.DAT[2873]",
        "$RCT2:OBJDATA/VEKST.DAT[2875]",
        "$RCT2:OBJDATA/VEKST.DAT[2877]",
        "$RCT2:OBJDATA/VEKST.DAT[2879]",
        "$RCT2:OBJDATA/VEKST.DAT[2881]",
        "$RCT2:OBJDATA/VEKST.DAT[2883]",
        "$RCT2:OBJDATA/VEKST.DAT[2885]",
        "$RCT2:OBJDATA/VEKST.DAT[2887]",
        "$RCT2:OBJDATA/VEKST.DAT[2889]",
        "$RCT2:OBJDATA/VEKST.DAT[2891]",
        "$RCT2:OBJDATA/VEKST.DAT[2893]",
        "$RCT2:OBJDATA/VEKST.DAT[2895]",
        "$RCT2:OBJDATA/VEKST.DAT[2897]",
        "$RCT2:OBJDATA/VEKST.DAT[2899]",
        "$RCT2:OBJDATA/VEKST.DAT[2901]",
        "$RCT2:OBJDATA/VEKST.DAT[2903]",
        "$RCT2:OBJDATA/VEKST.DAT[2905]",
        "$RCT2:OBJDATA/VEKST.DAT[3019..3062]",
        "$RCT2:OBJDATA/VEKST.DAT[3063]",
        "$RCT2:OBJDATA/VEKST.DAT[3065]",
        "$RCT2:OBJDATA/VEKST.DAT[3067]",
        "$RCT2:OBJDATA/VEKST.DAT[3069]",
        "$RCT2:OBJDATA/VEKST.DAT[3071]",
        "$RCT2:OBJDATA/VEKST.DAT[3073]",
        "$RCT2:OBJDATA/VEKST.DAT[3075]",
        "$RCT2:OBJDATA/VEKST.DAT[3077]",
        "$RCT2:OBJDATA/VEKST.DAT[3079]",
        "$RCT2:OBJDATA/VEKST.DAT[3081]",
        "$RCT2:OBJDATA/VEKST.DAT[3083]",
        "$RCT2:OBJDATA/VEKST.DAT[3085]",
        "$RCT2:OBJDATA/VEKST.DAT[3087]",
        "$RCT2:OBJDATA/VEKST.DAT[3089]",
        "$RCT2:OBJDATA/VEKST.DAT[3091]",
        "$RCT2:OBJDATA/VEKST.DAT[3093]",
        "$RCT2:OBJDATA/VEKST.DAT[3095]",
        "$RCT2:OBJDATA/VEKST.DAT[3097]",
        "$RCT2:OBJDATA/VEKST.DAT[3099]",
        "$RCT2:OBJDATA/VEKST.DAT[3101]",
        "$RCT2:OBJDATA/VEKST.DAT[3103]",
        "$RCT2:OBJDATA/VEKST.DAT[3105]",
        "$RCT2:OBJDATA/VEKST.DAT[3107]",
        "$RCT2:OBJDATA/VEKST.DAT[3109]",
        "$RCT2:OBJDATA/VEKST.DAT[3111]",
        "$RCT2:OBJDATA/VEKST.DAT[3113]",
        "$RCT2:OBJDATA/VEKST.DAT[3115]",
        "$RCT2:OBJDATA/VEKST.DAT[3117]",
        "$RCT2:OBJDATA/VEKST.DAT[3119]",
        "$RCT2:OBJDATA/VEKST.DAT[3121]",
        "$RCT2:OBJDATA/VEKST.DAT[3123]",
        "$RCT2:OBJDATA/VEKST.DAT[3125]",
        "$RCT2:OBJDATA/VEKST.DAT[3167]",
        "$RCT2:OBJDATA/VEKST.DAT[3175]",
        "$RCT2:OBJDATA/VEKST.DAT[3183]",
        "$RCT2:OBJDATA/VEKST.DAT[3191]",
        "$RCT2:OBJDATA/VEKST.DAT[3199]",
        "$RCT2:OBJDATA/VEKST.DAT[3207]",
        "$RCT2:OBJDATA/VEKST.DAT[3215]",
        "$RCT2:OBJDATA/VEKST.DAT[3223]",
        "$RCT2:OBJDATA/VEKST.DAT[3231]",
        "$RCT2:OBJDATA/VEKST.DAT[3239]",
        "$RCT2:OBJDATA/VEKST.DAT[3247]",
        "$RCT2:OBJDATA/VEKST.DAT[3255]",
        "$RCT2:OBJDATA/VEKST.DAT[3263]",
        "$RCT2:OBJDATA/VEKST.DAT[3271]",
        "$RCT2:OBJDATA/VEKST.DAT[3279]",
        "$RCT2:OBJDATA/VEKST.DAT[3287]",
        "$RCT2:OBJDATA/VEKST.DAT[3295..3310]",
        "$RCT2:OBJDATA/VEKST.DAT[3403]",
        "$RCT2:OBJDATA/VEKST.DAT[3405]",
        "$RCT2:OBJDATA/VEKST.DAT[3407]",
        "$RCT2:OBJDATA/VEKST.DAT[3409]",
        "$RCT2:OBJDATA/VEKST.DAT[3411]",
        "$RCT2:OBJDATA/VEKST.DAT[3413]",
        "$RCT2:OBJDATA/VEKST.DAT[3415]",
        "$RCT2:OBJDATA/VEKST.DAT[3417]",
        "$RCT2:OBJDATA/VEKST.DAT[3419]",
        "$RCT2:OBJDATA/VEKST.DAT[3421]",
        "$RCT2:OBJDATA/VEKST.DAT[3423]",
        "$RCT2:OBJDATA/VEKST.DAT[3425]",
        "$RCT2:OBJDATA/VEKST.DAT[3427]",
        "$RCT2:OBJDATA/VEKST.DAT[3429]",
        "$RCT2:OBJDATA/VEKST.DAT[3431]",
        "$RCT2:OBJDATA/VEKST.DAT[3433]",
        "$RCT2:OBJDATA/VEKST.DAT[3435..3442]",
        "$RCT2:OBJDATA/VEKST.DAT[3443]",
        "$RCT2:OBJDATA/VEKST.DAT[3445]",
        "$RCT2:OBJDATA/VEKST.DAT[3447]",
        "$RCT2:OBJDATA/VEKST.DAT[3449]",
        "$RCT2:OBJDATA/VEKST.DAT[3451]",
        "$RCT2:OBJDATA/VEKST.DAT[3453]",
        "$RCT2:OBJDATA/VEKST.DAT[3455]",
        "$RCT2:OBJDATA/VEKST.DAT[3457]",
        "$RCT2:OBJDATA/VEKST.DAT[3459]",
        "$RCT2:OBJDATA/VEKST.DAT[3461]",
        "$RCT2:OBJDATA/VEKST.DAT[3463]",
        "$RCT2:OBJDATA/VEKST.DAT[3465]",
        "$RCT2:OBJDATA/VEKST.DAT[3467]",
        "$RCT2:OBJDATA/VEKST.DAT[3469]",
        "$RCT2:OBJDATA/VEKST.DAT[3471]",
        "$RCT2:OBJDATA/VEKST.DAT[3473]",
        "$RCT2:OBJDATA/VEKST.DAT[3475]",
        "$RCT2:OBJDATA/VEKST.DAT[3477]",
        "$RCT2:OBJDATA/VEKST.DAT[3479]",
        "$RCT2:OBJDATA/VEKST.DAT[3481]",
        "$RCT2:OBJDATA/VEKST.DAT[3483]",
        "$RCT2:OBJDATA/VEKST.DAT[3485]",
        "$RCT2:OBJDATA/VEKST.DAT[3487]",
        "$RCT2:OBJDATA/VEKST.DAT[3489]",
        "$RCT2:OBJDATA/VEKST.DAT[3491]",
        "$RCT2:OBJDATA/VEKST.DAT[3493]",
        "$RCT2:OBJDATA/VEKST.DAT[3495]",
        "$RCT2:OBJDATA/VEKST.DAT[3497]",
        "$RCT2:OBJDATA/VEKST.DAT[3499]",
        "$RCT2:OBJDATA/VEKST.DAT[3501]",
        "$RCT2:OBJDATA/VEKST.DAT[3503]",
        "$RCT2:OBJDATA/VEKST.DAT[3505]",
        "$RCT2:OBJDATA/VEKST.DAT[3507..3522]",
        "$RCT2:OBJDATA/VEKST.DAT[3523]",
        "$RCT2:OBJDATA/VEKST.DAT[3525]",
        "$RCT2:OBJDATA/VEKST.DAT[3527]",
        "$RCT2:OBJDATA/VEKST.DAT[3529]",
        "$RCT2:OBJDATA/VEKST.DAT[3531]",
        "$RCT2:OBJDATA/VEKST.DAT[3533]",
        "$RCT2:OBJDATA/VEKST.DAT[3535]",
        "$RCT2:OBJDATA/VEKST.DAT[3537]",
        "$RCT2:OBJDATA/VEKST.DAT[3539]",
        "$RCT2:OBJDATA/VEKST.DAT[3541]",
        "$RCT2:OBJDATA/VEKST.DAT[3543]",
        "$RCT2:OBJDATA/VEKST.DAT[3545]",
        "$RCT2:OBJDATA/VEKST.DAT[3547]",
        "$RCT2:OBJDATA/VEKST.DAT[3549]",
        "$RCT2:OBJDATA/VEKST.DAT[3551]",
        "$RCT2:OBJDATA/VEKST.DAT[3553]",
        "$RCT2:OBJDATA/VEKST.DAT[3555]",
        "$RCT2:OBJDATA/VEKST.DAT[3557]",
        "$RCT2:OBJDATA/VEKST.DAT[3559]",
        "$RCT2:OBJDATA/VEKST.DAT[3561]",
        "$RCT2:OBJDATA/VEKST.DAT[3563]",
        "$RCT2:OBJDATA/VEKST.DAT[3565]",
        "$RCT2:OBJDATA/VEKST.DAT[3567]",
        "$RCT2:OBJDATA/VEKST.DAT[3569]",
        "$RCT2:OBJDATA/VEKST.DAT[3571]",
        "$RCT2:OBJDATA/VEKST.DAT[3573]",
        "$RCT2:OBJDATA/VEKST.DAT[3575]",
        "$RCT2:OBJDATA/VEKST.DAT[3577]",
        "$RCT2:OBJDATA/VEKST.DAT[3579]",
        "$RCT2:OBJDATA/VEKST.DAT[3581]",
        "$RCT2:OBJDATA/VEKST.DAT[3583]",
        "$RCT2:OBJDATA/VEKST.DAT[3585]",
        "$RCT2:OBJDATA/VEKST.DAT[3699..3742]",
        "$RCT2:OBJDATA/VEKST.DAT[3743]",
        "$RCT2:OBJDATA/VEKST.DAT[3745]",
        "$RCT2:OBJDATA/VEKST.DAT[3747]",
        "$RCT2:OBJDATA/VEKST.DAT[3749]",
        "$RCT2:OBJDATA/VEKST.DAT[3751]",
        "$RCT2:OBJDATA/VEKST.DAT[3753]",
        "$RCT2:OBJDATA/VEKST.DAT[3755]",
        "$RCT2:OBJDATA/VEKST.DAT[3757]",
        "$RCT2:OBJDATA/VEKST.DAT[3759]",
        "$RCT2:OBJDATA/VEKST.DAT[3761]",
        "$RCT2:OBJDATA/VEKST.DAT[3763]",
        "$RCT2:OBJDATA/VEKST.DAT[3765]",
        "$RCT2:OBJDATA/VEKST.DAT[3767]",
        "$RCT2:OBJDATA/VEKST.DAT[3769]",
        "$RCT2:OBJDATA/VEKST.DAT[3771]",
        "$RCT2:OBJDATA/VEKST.DAT[3773]",
        "$RCT2:OBJDATA/VEKST.DAT[3775]",
        "$RCT2:OBJDATA/VEKST.DAT[3777]",
        "$RCT2:OBJDATA/VEKST.DAT[3779]",
        "$RCT2:OBJDATA/VEKST.DAT[3781]",
        "$RCT2:OBJDATA/VEKST.DAT[3783]",
        "$RCT2:OBJDATA/VEKST.DAT[3785]",
        "$RCT2:OBJDATA/VEKST.DAT[3787]",
        "$RCT2:OBJDATA/VEKST.DAT[3789]",
        "$RCT2:OBJDATA/VEKST.DAT[3791]",
        "$RCT2:OBJDATA/VEKST.DAT[3793]",
        "$RCT2:OBJDATA/VEKST.DAT[3795]",
        "$RCT2:OBJDATA/VEKST.DAT[3797]",
        "$RCT2:OBJDATA/VEKST.DAT[3799]",
        "$RCT2:OBJDATA/VEKST.DAT[3801]",
        "$RCT2:OBJDATA/VEKST.DAT[3803]",
        "$RCT2:OBJDATA/VEKST.DAT[3805]",
        "$RCT2:OBJDATA/VEKST.DAT[3847]",
        "$RCT2:OBJDATA/VEKST.DAT[3855]",
        "$RCT2:OBJDATA/VEKST.DAT[3863]",
        "$RCT2:OBJDATA/VEKST.DAT[3871]",
        "$RCT2:OBJDATA/VEKST.DAT[3879]",
        "$RCT2:OBJDATA/VEKST.DAT[3887]",
        "$RCT2:OBJDATA/VEKST.DAT[3895]",
        "$RCT2:OBJDATA/VEKST.DAT[3903]",
        "$RCT2:OBJDATA/VEKST.DAT[3911]",
        "$RCT2:OBJDATA/VEKST.DAT[3919]",
        "$RCT2:OBJDATA/VEKST.DAT[3927]",
        "$RCT2:OBJDATA/VEKST.DAT[3935]",
        "$RCT2:OBJDATA/VEKST.DAT[3943]",
        "$RCT2:OBJDATA/VEKST.DAT[3951]",
        "$RCT2:OBJDATA/VEKST.DAT[3959]",
        "$RCT2:OBJDATA/VEKST.DAT[3967]",
        "$RCT2:OBJDATA/VEKST.DAT[3975..3990]"
    ],
    "strings": {
        "name": {
            "en-GB": "Lay-down Roller Coaster Trains",
            "fr-FR": "Train de montagnes russes en position couche",
            "de-DE": "Liegeachterbahnzge",
            "es-ES": "Montaa Rusa Fija",
            "it-IT": "Ottovolante in pos. distesa",
            "nl-NL": "Trein voor liggende achtbaan",
            "sv-SE": "Liggvagnar",
            "ko-KR": "   ",
            "zh-CN": "",
            "zh-TW": "",
            "pt-BR": "Trens Montanha-Russa Deitada",
            "cs-CZ": "Horsk drha \"na leka\"",
            "ja-JP": "",
            "pl-PL": "Leca kolejka",
            "ru-RU": " ",
            "eo-ZZ": "Trajnoj de Kuianta Onda Fervojo",
            "ca-ES": "Muntanya russa amb passatgers gitats en trens",
            "fi-FI": "Makuuvuoristoratavaunut"
        },
        "description": {
            "en-GB": "Riders are held in special harnesses in a lying-down position, travelling either on their backs or facing the ground",
            "en-US": "Riders are held in special harnesses in a lying-down position, traveling either on their backs or facing the ground",
            "fr-FR": "Les passagers sont couchs  plat ventre ou sur le dos, et maintenus par des harnais spciaux",
            "de-DE": "Die Passagiere befinden sich in speziellen Haltevorrichtungen in liegender Position und fahren entweder auf dem Rcken oder dem Bauch",
            "es-ES": "Los pasajeros estn sujetos por unos arneses cara abajo",
            "it-IT": "I passeggeri sono tenuti distesi da speciali bardature e viaggiano lungo un tracciato contorto caratterizzato da inversioni, guardando ora per terra ora verso il cielo",
            "nl-NL": "Passagiers worden door middel van een speciale beugel in een liggende positie vastgehouden, waarna ze op hun rug of met hun gezicht naar de grond door kronkelende stukken baan en omkeringen heen gaan.",
            "sv-SE": "Passagerarnas spnns fast liggande i speciella seldon, och ker antingen p rygg eller med ansiktet mot marken",
            "ko-KR": "              ",
            "zh-CN": ",,",
            "zh-TW": ",,",
            "pt-BR": "Os passageiros so colocados em assentos especiais na posio horizontal, deitados para cima ou para baixo",
            "cs-CZ": "Nvtvnci jedou v lee zaveni do specilnho dren, ve kterm na bie projedou tra s ostrmi zatkami",
            "ja-JP": "",
            "pl-PL": "Pasaerowie wisz w specjalnych uprzach twarz w d, podrujc przez zakrcony tor albo na plecach, albo twarz ku ziemi",
            "ru-RU": "      ,      ,   ",
            "eo-ZZ": "Rajdantoj kuiantaj estas tenitaj en specialaj jungaoj, kaj veturas a fronte al la ielo a fronte al la tero",
            "ca-ES": "Els passatgers estan lligats en arnesos gitats, movent-se mentre estan cara amunt o cara avall.",
            "fi-FI": "Matkustajat laitetaan makuuasentoon erikoisvaljaisiin, ja laitetaan kiitmn kiemurtelevan ja kntyilevn radan lpi, joko selin tai vatsallaan"
        },
        "capacity": {
            "en-GB": "4 passengers per car",
            "fr-FR": "4 passagers par voiture",
            "de-DE": "4 Fahrgste pro Wagen",
            "es-ES": "4 pasajeros por vagn",
            "it-IT": "4 passeggeri a carrozza",
            "nl-NL": "4 passagiers per karretje",
            "sv-SE": "4 passagerare per vagn",
            "ko-KR": " 4 ",
            "zh-CN": "4/",
            "zh-TW": "4 /",
            "pt-BR": "4 passageiros por vago",
            "cs-CZ": "4 msta v kadm voze",
            "ja-JP": "4",
            "pl-PL": "4 pasaerw na wagonik",
            "ru-RU": "4   ",
            "eo-ZZ": "Po 4 pasaeroj por aro",
            "ca-ES": "4 passatgers per cotxe",
            "fi-FI": "4 matkustajaa per vaunu"
        }
    }
}
