{
    "id": "rct2.ww.rdrab03",
    "authors": ["Frontier Studios"],
    "version": "1.0",
    "originalId": "0CBD0A12|RDRAB03 |37AB4315",
    "sourceGame": "rct2ww",
    "objectType": "scenery_large",
    "properties": {
        "price": 190,
        "removalPrice": -150,
        "cursor": "CURSOR_HOUSE_DOWN",
        "tiles": [
            {
                "x": 0,
                "y": 0,
                "clearance": 96,
                "walls": 9
            },
            {
                "x": 0,
                "y": 32,
                "clearance": 96,
                "walls": 3
            },
            {
                "x": 32,
                "y": 0,
                "clearance": 96,
                "walls": 8
            },
            {
                "x": 32,
                "y": 32,
                "clearance": 96,
                "walls": 2
            }
        ]
    },
    "images": ["$RCT2:OBJDATA/RDRAB03.DAT[0..19]"],
    "strings": {
        "name": {
            "en-GB": "Drab Large Tower Top",
            "fr-FR": "Sommet de grande tour terne",
            "de-DE": "Düsterer Großer Turm - Spitze",
            "es-ES": "Cima de torre grande apagada",
            "it-IT": "Sommità di torre grande smorta",
            "nl-NL": "Vale top grote toren",
            "sv-SE": "Stor gråbrun torntopp",
            "cs-CZ": "Velká věž",
            "ko-KR": "칙칙한 대형 탑 상단",
            "pl-PL": "Płowa wieża - szczyt",
            "ru-RU": "Деталь башни",
            "pt-BR": "Topo da Grande Torre Gris"
        }
    }
}
